Workbook

Sheet Feuille 1
A1: POST NUMBER | B1: POST DATASET ID | C1: POST | D1: Target Group | E1: Target Group (Id. by Grok) | F1: Target Group (Id by Claude) | G1: Human #1 | H1: Human #2 | I1: Grok | J1: Claude AI | K1: Human Annotator #1 | L1: Human Annotator #2 | M1: Platform of Origin | N1: Study Annotator #1 Classification | O1: Study Annotator #1 Target Group | P1: Study Annotator #2 Classification | Q1: Study Annotator #2 Target Group | R1: Study Annotator #3 Classification | S1: Study Annotator #3 Target Group | T1: "Normal" Class. Count | U1: "Offensive" Class. Count | V1: "Hate Speech" Class. Count | W1: Completeness Score | X1: Majority? | Y1: Standard Deviation
A2: 001 | B2: 21376810_gab | C2: exactly if a low iq nigger from africa who can not read can understand islam i think i can understand kill the kuffar nothing subtle lost on me | D2: African, Muslim | E2: AfricanBlack, Muslim | F2: Black people, Muslims | G2: Offensive | H2: Offensive | I2: Hate Speech | J2: Hate Speech | K2: GM#5 | L2: GM#4 | M2: Gab | N2: hatespeech | O2: African | P2: hatespeech | Q2: African, Buddhism | R2: hatespeech | S2: African | T2: =COUNTIF(G2:J2,"*Normal*") -> 0 | U2: =COUNTIF(G2:J2,"*Offensive*") -> 2 | V2: =COUNTIF(G2:J2,"*Hate Speech*") -> 2 | W2: =SUM(T2:V2)/4 -> 1 | X2: =IF(T2>2,"Normal", IF(U2>2, "Offensive", IF(V2>2, "Hate Speech"))) -> FALSE | Y2: =STDEV(T2:V2) -> 1.1547005
A3: 002 | B3: 1080843707643944965_twitter | C3: <user> yes because it is and i sound so broken bitch when did i have feelings | D3: None | E3: Women | F3: N/A | G3: Normal | H3: Normal | I3: Offensive | J3: Normal | K3: GM#5 | L3: GM#3 | M3: Twitter | N3: normal | O3: None | P3: offensive | Q3: None | R3: normal | S3: Women | T3: =COUNTIF(G3:J3,"*Normal*") -> 3 | U3: =COUNTIF(G3:J3,"*Offensive*") -> 1 | V3: =COUNTIF(G3:J3,"*Hate Speech*") -> 0 | W3: =SUM(T3:V3)/4 -> 1 | X3: =IF(T3>2,"Normal", IF(U3>2, "Offensive", IF(V3>2, "Hate Speech"))) -> Normal | Y3: =STDEV(T3:V3) -> 1.5275252
A4: 003 | B4: 1178183797461811200_twitter | C4: a white man tired to slide the phase i was the nigger when describing his up bringing in japan tonight at dinner white privilege continues to be heavy people have such low level of compassion no one is hiding their racism anymore | D4: African | E4: AfricanBlack | F4: Black people | G4: Normal | H4: Normal | I4: Hate Speech | J4: Hate Speech | K4: GM#5 | L4: GM#1 | M4: Twitter | N4: normal | O4: None | P4: normal | Q4: None | R4: normal | S4: None | T4: =COUNTIF(G4:J4,"*Normal*") -> 2 | U4: =COUNTIF(G4:J4,"*Offensive*") -> 0 | V4: =COUNTIF(G4:J4,"*Hate Speech*") -> 2 | W4: =SUM(T4:V4)/4 -> 1 | X4: =IF(T4>2,"Normal", IF(U4>2, "Offensive", IF(V4>2, "Hate Speech"))) -> FALSE | Y4: =STDEV(T4:V4) -> 1.1547005
A5: 004 | B5: 1178917247626203136_twitter | C5: <user> <user> <user> <user> <user> trump said he loves the educated he loves the uneducated he loves men he loves women he loves legal immigrants he loves americans people with severe tds omg trump said he prefers dumb white uneducated men | D5: Education, Woman, Immigrant, Americans, | E5: White People | F5: N/A | G5: Normal | H5: Offensive | I5: Normal | J5: Normal | K5: GM#5 | L5: GM#2 | M5: Twitter | N5: normal | O5: None | P5: normal | Q5: None | R5: offensive | S5: Caucasian | T5: =COUNTIF(G5:J5,"*Normal*") -> 3 | U5: =COUNTIF(G5:J5,"*Offensive*") -> 1 | V5: =COUNTIF(G5:J5,"*Hate Speech*") -> 0 | W5: =SUM(T5:V5)/4 -> 1 | X5: =IF(T5>2,"Normal", IF(U5>2, "Offensive", IF(V5>2, "Hate Speech"))) -> Normal | Y5: =STDEV(T5:V5) -> 1.5275252
A6: 005 | B6: 19332653_gab | C6: rotherham is the trigger for the world whites allowing the rape of white children by paki muslims and covered up for diversity means many mps councillors police should be swinging from a rope and any fucked up media rep who refuses to see the truth | D6: Muslim | E6: Muslim, Asian (Pakistani) | F6: Muslims, Politicians | G6: Hate Speech | H6: Offensive | I6: Hate Speech | J6: Hate Speech | K6: GM#5 | L6: GM#4 | M6: Gab | N6: normal | O6: None | P6: normal | Q6: None | R6: normal | S6: None | T6: =COUNTIF(G6:J6,"*Normal*") -> 0 | U6: =COUNTIF(G6:J6,"*Offensive*") -> 1 | V6: =COUNTIF(G6:J6,"*Hate Speech*") -> 3 | W6: =SUM(T6:V6)/4 -> 1 | X6: =IF(T6>2,"Normal", IF(U6>2, "Offensive", IF(V6>2, "Hate Speech"))) -> Hate Speech | Y6: =STDEV(T6:V6) -> 1.5275252
A7: 006 | B7: 9841810_gab | C7: jews couch their distrust of whites as if it were a logical response to random violence that we routinely heap upon them because of our barbaric gentile ways the truth though is that they want us gone because we are the only ones who routinely oppose their nefarious schemes for domination | D7: Jewish | E7: Jewish people | F7: Jewish people | G7: Offensive | H7: Offensive | I7: Hate Speech | J7: Hate Speech | K7: GM#5 | L7: GM#3 | M7: Gab | N7: offensive | O7: Jewish | P7: normal | Q7: Jewish | R7: normal | S7: None | T7: =COUNTIF(G7:J7,"*Normal*") -> 0 | U7: =COUNTIF(G7:J7,"*Offensive*") -> 2 | V7: =COUNTIF(G7:J7,"*Hate Speech*") -> 2 | W7: =SUM(T7:V7)/4 -> 1 | X7: =IF(T7>2,"Normal", IF(U7>2, "Offensive", IF(V7>2, "Hate Speech"))) -> FALSE | Y7: =STDEV(T7:V7) -> 1.1547005
A8: 007 | B8: 1218921638139326467_twitter | C8: i need my back cracked like a mf glow stick by them tiny little asians in la | D8: Asian | E8: ChineseAsian | F8: N/A | G8: Offensive | H8: Normal | I8: Offensive | J8: Normal | K8: GM#5 | L8: GM#1 | M8: Twitter | N8: offensive | O8: Asian | P8: normal | Q8: Asian | R8: offensive | S8: Asian, Women | T8: =COUNTIF(G8:J8,"*Normal*") -> 2 | U8: =COUNTIF(G8:J8,"*Offensive*") -> 2 | V8: =COUNTIF(G8:J8,"*Hate Speech*") -> 0 | W8: =SUM(T8:V8)/4 -> 1 | X8: =IF(T8>2,"Normal", IF(U8>2, "Offensive", IF(V8>2, "Hate Speech"))) -> FALSE | Y8: =STDEV(T8:V8) -> 1.1547005
A9: 008 | B9: 1087224984639033344_twitter | C9: <user> if u were askin her out would she not realize ur not gay | D9: Homosexual | E9: LGBTQ+ | F9: N/A | G9: Offensive | H9: Normal | I9: Offensive | J9: Normal | K9: GM#5 | L9: GM#2 | M9: Twitter | N9: normal | O9: Homosexual | P9: normal | Q9: Homosexual | R9: normal | S9: Homosexual | T9: =COUNTIF(G9:J9,"*Normal*") -> 2 | U9: =COUNTIF(G9:J9,"*Offensive*") -> 2 | V9: =COUNTIF(G9:J9,"*Hate Speech*") -> 0 | W9: =SUM(T9:V9)/4 -> 1 | X9: =IF(T9>2,"Normal", IF(U9>2, "Offensive", IF(V9>2, "Hate Speech"))) -> FALSE | Y9: =STDEV(T9:V9) -> 1.1547005
A10: 009 | B10: 1178639561502707713_twitter | C10: this happens a lot in the makeup beauty community gay men think that the women who have a problem with drag queens or with gay men using misogynistic slurs etc all must be str8 girls who do not know how the lgbt community works guess what dykes hate you too | D10: Homosexual | E10: Homosexual, Queer | F10: Gay men, Women | G10: Offensive | H10: Offensive | I10: Offensive | J10: Offensive | K10: GM#5 | L10: GM#4 | M10: Twitter | N10: normal | O10: None | P10: normal | Q10: None | R10: normal | S10: None | T10: =COUNTIF(G10:J10,"*Normal*") -> 0 | U10: =COUNTIF(G10:J10,"*Offensive*") -> 4 | V10: =COUNTIF(G10:J10,"*Hate Speech*") -> 0 | W10: =SUM(T10:V10)/4 -> 1 | X10: =IF(T10>2,"Normal", IF(U10>2, "Offensive", IF(V10>2, "Hate Speech"))) -> Offensive | Y10: =STDEV(T10:V10) -> 2.3094011
A11: 010 | B11: 20156398_gab | C11: of course there will always be white actors and actresses it just they are slated to always play villains and nigger whores western pop culture is devolving into niggerdom at such frightening pace it truly is painful to watch | D11: African, Woman | E11: Black people | F11: Black people | G11: Offensive | H11: Offensive | I11: Hate Speech | J11: Hate Speech | K11: GM#5 | L11: GM#3 | M11: Gab | N11: hatespeech | O11: Women, African | P11: hatespeech | Q11: African, Women | R11: hatespeech | S11: African | T11: =COUNTIF(G11:J11,"*Normal*") -> 0 | U11: =COUNTIF(G11:J11,"*Offensive*") -> 2 | V11: =COUNTIF(G11:J11,"*Hate Speech*") -> 2 | W11: =SUM(T11:V11)/4 -> 1 | X11: =IF(T11>2,"Normal", IF(U11>2, "Offensive", IF(V11>2, "Hate Speech"))) -> FALSE | Y11: =STDEV(T11:V11) -> 1.1547005
A12: 011 | B12: 1080898632050724864_twitter | C12: gt raped by light <user> <user> | D12: None | E12: Victims of SA | F12: Women | G12: Offensive | H12: Offensive | I12: Offensive | J12: Offensive | K12: GM#5 | L12: GM#1 | M12: Twitter | N12: offensive | O12: None | P12: normal | Q12: None | R12: offensive | S12: None | T12: =COUNTIF(G12:J12,"*Normal*") -> 0 | U12: =COUNTIF(G12:J12,"*Offensive*") -> 4 | V12: =COUNTIF(G12:J12,"*Hate Speech*") -> 0 | W12: =SUM(T12:V12)/4 -> 1 | X12: =IF(T12>2,"Normal", IF(U12>2, "Offensive", IF(V12>2, "Hate Speech"))) -> Offensive | Y12: =STDEV(T12:V12) -> 2.3094011
A13: 012 | B13: 2644271_gab | C13: fakenews that would be the mainstream media cnn msm msnbc cbs nbc etc so please stop blaming us the voter and the alternative media for your stupidity and you going full retard | D13: Journalists, Liberal | E13: Liberals / Media | F13: N/A | G13: Offensive | H13: Offensive | I13: Offensive | J13: Normal | K13: GM#5 | L13: GM#2 | M13: Gab | N13: normal | O13: None | P13: offensive | Q13: Other | R13: offensive | S13: None | T13: =COUNTIF(G13:J13,"*Normal*") -> 1 | U13: =COUNTIF(G13:J13,"*Offensive*") -> 3 | V13: =COUNTIF(G13:J13,"*Hate Speech*") -> 0 | W13: =SUM(T13:V13)/4 -> 1 | X13: =IF(T13>2,"Normal", IF(U13>2, "Offensive", IF(V13>2, "Hate Speech"))) -> Offensive | Y13: =STDEV(T13:V13) -> 1.5275252
A14: 013 | B14: 1181320554227359745_twitter | C14: <user> whoever picked mineecraft is fuckign retarded | D14: None | E14: Disability | F14: People with disabilities | G14: Offensive | I14: Offensive | J14: Offensive | K14: GM#5 | L14: GM#4 | M14: Twitter | N14: offensive | O14: Other | P14: offensive | Q14: None | R14: offensive | S14: None | T14: =COUNTIF(G14:J14,"*Normal*") -> 0 | U14: =COUNTIF(G14:J14,"*Offensive*") -> 3 | V14: =COUNTIF(G14:J14,"*Hate Speech*") -> 0 | W14: =SUM(T14:V14)/4 -> 0.75 | X14: =IF(T14>2,"Normal", IF(U14>2, "Offensive", IF(V14>2, "Hate Speech"))) -> Offensive | Y14: =STDEV(T14:V14) -> 1.7320508
A15: 014 | B15: 12856688_gab | C15: two terror attacks on anglo american cities in one night when is enough enough tolerance is the virtue of a dying society trump better come down hard a moslem ban is a good start but we need an exit strategy we need to deport all moslems now lasvegas canadaterrorattack edmonton | D15: Muslim | E15: Muslim people | F15: N/A | G15: Hate Speech | H15: Offensive | I15: Hate Speech | J15: Normal | K15: GM#5 | L15: GM#3 | M15: Gab | N15: hatespeech | O15: Islam | P15: hatespeech | Q15: Arab, Islam | R15: offensive | S15: Islam | T15: =COUNTIF(G15:J15,"*Normal*") -> 1 | U15: =COUNTIF(G15:J15,"*Offensive*") -> 1 | V15: =COUNTIF(G15:J15,"*Hate Speech*") -> 2 | W15: =SUM(T15:V15)/4 -> 1 | X15: =IF(T15>2,"Normal", IF(U15>2, "Offensive", IF(V15>2, "Hate Speech"))) -> FALSE | Y15: =STDEV(T15:V15) -> 0.57735027
A16: 015 | B16: 13279118_gab | C16: weak milquetoast faggots like you will never change america you are just another civic nationalist cuckold pussy too scared to even talk about race because you are such a chickenshit so scared like a woman of being called a wayciss or a white supwemasiss lol what a nutless coward | D16: Homosexual | E16: Homosexual, Caucasian | F16: Gay people | G16: Offensive | I16: Hate Speech | J16: Offensive | K16: GM#5 | L16: GM#1 | M16: Gab | N16: hatespeech | O16: Homosexual, Women | P16: hatespeech | Q16: Homosexual, Caucasian, Women | R16: offensive | S16: Homosexual, Women | T16: =COUNTIF(G16:J16,"*Normal*") -> 0 | U16: =COUNTIF(G16:J16,"*Offensive*") -> 2 | V16: =COUNTIF(G16:J16,"*Hate Speech*") -> 1 | W16: =SUM(T16:V16)/4 -> 0.75 | X16: =IF(T16>2,"Normal", IF(U16>2, "Offensive", IF(V16>2, "Hate Speech"))) -> FALSE | Y16: =STDEV(T16:V16) -> 1
A17: 016 | B17: 4464004_gab | C17: journalists are showing themselves to be the retarded liberals they are the tradition of ap can die the traditional press corps can die in gas station bathrooms | D17: Journalists, Liberal | E17: Liberals / Media | F17: People with disabilities, Liberals | G17: Offensive | H17: Hate Speech | I17: Offensive | J17: Offensive | K17: GM#5 | L17: GM#2 | M17: Gab | N17: hatespeech | O17: Other | P17: offensive | Q17: Other | R17: offensive | S17: None | T17: =COUNTIF(G17:J17,"*Normal*") -> 0 | U17: =COUNTIF(G17:J17,"*Offensive*") -> 3 | V17: =COUNTIF(G17:J17,"*Hate Speech*") -> 1 | W17: =SUM(T17:V17)/4 -> 1 | X17: =IF(T17>2,"Normal", IF(U17>2, "Offensive", IF(V17>2, "Hate Speech"))) -> Offensive | Y17: =STDEV(T17:V17) -> 1.5275252
A18: 017 | B18: 1178643287873335296_twitter | C18: feel phylliscitations to daff mr hairwigger who has just hadded twinned little curls he was resting between horrockses sheets wailing for white warfare prooboor welsht breton | E18: AfricanBlack, Caucasian | F18: N/A | I18: Hate Speech | J18: Normal | K18: GM#5 | L18: GM#4 | M18: Twitter | N18: normal | O18: None | P18: normal | Q18: None | R18: normal | S18: None | T18: =COUNTIF(G18:J18,"*Normal*") -> 1 | U18: =COUNTIF(G18:J18,"*Offensive*") -> 0 | V18: =COUNTIF(G18:J18,"*Hate Speech*") -> 1 | W18: =SUM(T18:V18)/4 -> 0.5 | X18: =IF(T18>2,"Normal", IF(U18>2, "Offensive", IF(V18>2, "Hate Speech"))) -> FALSE | Y18: =STDEV(T18:V18) -> 0.57735027
A19: 018 | B19: 4496379_gab | C19: detention space for illegal immigrants oh my dare i say concentration camps gas the spics border war now in all seriousness detention camps are necessary you can not let beaners roam around raping and pillaging you have to lock up all the taco niggers until you are ready to remove them | D19: Immigrant, African | E19: Hispanic people, Black people | F19: Hispanic people | G19: Hate Speech | H19: Hate Speech | I19: Hate Speech | J19: Hate Speech | K19: GM#5 | L19: GM#3 | M19: Gab | N19: offensive | O19: Hispanic | P19: hatespeech | Q19: Hispanic | R19: hatespeech | S19: Refugee, Hispanic | T19: =COUNTIF(G19:J19,"*Normal*") -> 0 | U19: =COUNTIF(G19:J19,"*Offensive*") -> 0 | V19: =COUNTIF(G19:J19,"*Hate Speech*") -> 4 | W19: =SUM(T19:V19)/4 -> 1 | X19: =IF(T19>2,"Normal", IF(U19>2, "Offensive", IF(V19>2, "Hate Speech"))) -> Hate Speech | Y19: =STDEV(T19:V19) -> 2.3094011
A20: 019 | B20: 1086417563444232194_twitter | C20: <user> let be honest multiculturalism is just a euphemism for hostile takeover by jews and non whites | D20: Jewish | E20: Jewish | F20: Jewish people | G20: Offensive | H20: Offensive | I20: Hate Speech | J20: Hate Speech | K20: GM#5 | L20: GM#1 | M20: Twitter | N20: offensive | O20: African, Arab, Asian, Hispanic, Jewish | P20: hatespeech | Q20: Jewish | R20: hatespeech | S20: Other | T20: =COUNTIF(G20:J20,"*Normal*") -> 0 | U20: =COUNTIF(G20:J20,"*Offensive*") -> 2 | V20: =COUNTIF(G20:J20,"*Hate Speech*") -> 2 | W20: =SUM(T20:V20)/4 -> 1 | X20: =IF(T20>2,"Normal", IF(U20>2, "Offensive", IF(V20>2, "Hate Speech"))) -> FALSE | Y20: =STDEV(T20:V20) -> 1.1547005
A21: 020 | B21: 23292228_gab | C21: basically if the democrats want something it because they figure that in the long run it makes it easier for gay latino muslims to rape your kids mpcstatusupdates | D21: Democrat, Latino, Muslim | E21: Muslim, Latino, LGBTQ+ | F21: N/A | G21: Offensive | H21: Offensive | I21: Hate Speech | J21: Normal | K21: GM#5 | L21: GM#2 | M21: Gab | N21: hatespeech | O21: Hispanic, Islam | P21: hatespeech | Q21: Homosexual, Arab, Hispanic, Islam, Men, Women | R21: offensive | S21: Arab, Hispanic, Islam | T21: =COUNTIF(G21:J21,"*Normal*") -> 1 | U21: =COUNTIF(G21:J21,"*Offensive*") -> 2 | V21: =COUNTIF(G21:J21,"*Hate Speech*") -> 1 | W21: =SUM(T21:V21)/4 -> 1 | X21: =IF(T21>2,"Normal", IF(U21>2, "Offensive", IF(V21>2, "Hate Speech"))) -> FALSE | Y21: =STDEV(T21:V21) -> 0.57735027
A22: 021 | B22: 21333143_gab | C22: are they 2 nd 3 rd 4 th wives the muslim child birth rate is out of control and the <number> bastard are letting it carry on they really believe that soft politics will curb their desire to have a calliohate in the uk <number> mps and so delusional and dangerous | D22: Muslim | E22: Muslim | F22: Muslims | G22: Offensive | H22: Offensive | I22: Hate Speech | J22: Hate Speech | K22: GM#5 | L22: GM#4 | M22: Gab | N22: offensive | O22: Arab, Islam | P22: hatespeech | Q22: Islam | R22: offensive | S22: Islam | T22: =COUNTIF(G22:J22,"*Normal*") -> 0 | U22: =COUNTIF(G22:J22,"*Offensive*") -> 2 | V22: =COUNTIF(G22:J22,"*Hate Speech*") -> 2 | W22: =SUM(T22:V22)/4 -> 1 | X22: =IF(T22>2,"Normal", IF(U22>2, "Offensive", IF(V22>2, "Hate Speech"))) -> FALSE | Y22: =STDEV(T22:V22) -> 1.1547005
A23: 022 | B23: 12787888_gab | C23: it a proven medical fact that retards do not know how to use punctuation in a sentence it also a fact that only a homo can tolerate homos do you pitch or catch or both | D23: Homosexual, Disabled | E23: People with disabilities, Gay people | F23: Gay people, People with disabilities | G23: Offensive | H23: Offensive | I23: Offensive | J23: Hate Speech | K23: GM#5 | L23: GM#3 | M23: Gab | N23: offensive | O23: Homosexual, Men, Other | P23: offensive | Q23: Homosexual | R23: hatespeech | S23: Homosexual, Other | T23: =COUNTIF(G23:J23,"*Normal*") -> 0 | U23: =COUNTIF(G23:J23,"*Offensive*") -> 3 | V23: =COUNTIF(G23:J23,"*Hate Speech*") -> 1 | W23: =SUM(T23:V23)/4 -> 1 | X23: =IF(T23>2,"Normal", IF(U23>2, "Offensive", IF(V23>2, "Hate Speech"))) -> Offensive | Y23: =STDEV(T23:V23) -> 1.5275252
A24: 023 | B24: 2901472_gab | C24: <user> he should resign and then commit hara kiri in front of those bloody thirsty muslim scumbag camel jockeys | D24: Muslim | E24: Muslim, Arab | F24: Muslims | G24: Offensive | H24: Hate Speech | I24: Hate Speech | J24: Hate Speech | K24: GM#5 | L24: GM#1 | M24: Gab | N24: hatespeech | O24: Arab, Islam, Men, Women | P24: hatespeech | Q24: Islam | R24: hatespeech | S24: Islam | T24: =COUNTIF(G24:J24,"*Normal*") -> 0 | U24: =COUNTIF(G24:J24,"*Offensive*") -> 1 | V24: =COUNTIF(G24:J24,"*Hate Speech*") -> 3 | W24: =SUM(T24:V24)/4 -> 1 | X24: =IF(T24>2,"Normal", IF(U24>2, "Offensive", IF(V24>2, "Hate Speech"))) -> Hate Speech | Y24: =STDEV(T24:V24) -> 1.5275252
A25: 024 | B25: 1179086548907610113_twitter | C25: <user> i am trynna make it a non gay offensive slur lol i only call non gays faggots you a faggot if you got some bitchassness in you feel me | D25: Homosexual | E25: LGBTQ+ | F25: Gay people | G25: Offensive | H25: Normal | I25: Offensive | J25: Offensive | K25: GM#5 | L25: GM#2 | M25: Twitter | N25: offensive | O25: Homosexual | P25: offensive | Q25: Homosexual | R25: hatespeech | S25: Homosexual | T25: =COUNTIF(G25:J25,"*Normal*") -> 1 | U25: =COUNTIF(G25:J25,"*Offensive*") -> 3 | V25: =COUNTIF(G25:J25,"*Hate Speech*") -> 0 | W25: =SUM(T25:V25)/4 -> 1 | X25: =IF(T25>2,"Normal", IF(U25>2, "Offensive", IF(V25>2, "Hate Speech"))) -> Offensive | Y25: =STDEV(T25:V25) -> 1.5275252
A26: 025 | B26: 14879780_gab | C26: attacking the retard left is lame any way they block you for saying nices things to them | D26: Liberal, Disability | E26: Disability | F26: People with disabilities | G26: Normal | H26: Offensive | I26: Offensive | J26: Offensive | K26: GM#5 | L26: GM#4 | M26: Gab | N26: offensive | O26: Men, Women, Other | P26: offensive | Q26: None | R26: offensive | S26: None | T26: =COUNTIF(G26:J26,"*Normal*") -> 1 | U26: =COUNTIF(G26:J26,"*Offensive*") -> 3 | V26: =COUNTIF(G26:J26,"*Hate Speech*") -> 0 | W26: =SUM(T26:V26)/4 -> 1 | X26: =IF(T26>2,"Normal", IF(U26>2, "Offensive", IF(V26>2, "Hate Speech"))) -> Offensive | Y26: =STDEV(T26:V26) -> 1.5275252
A27: 026 | B27: 1164945865603211264_twitter | C27: i ain ’ t even gone speak on it just know niggas ain ’ t who they claim to be on this social media shit | D27: None | E27: - | F27: Black people | G27: Normal | H27: Normal | I27: Offensive | J27: Offensive | K27: GM#5 | L27: GM#3 | M27: Twitter | N27: offensive | O27: African | P27: normal | Q27: Men, Women | R27: offensive | S27: African | T27: =COUNTIF(G27:J27,"*Normal*") -> 2 | U27: =COUNTIF(G27:J27,"*Offensive*") -> 2 | V27: =COUNTIF(G27:J27,"*Hate Speech*") -> 0 | W27: =SUM(T27:V27)/4 -> 1 | X27: =IF(T27>2,"Normal", IF(U27>2, "Offensive", IF(V27>2, "Hate Speech"))) -> FALSE | Y27: =STDEV(T27:V27) -> 1.1547005
A28: 027 | B28: 24683696_gab | C28: lil fag is also a wannabe sand nigger | D28: Homosexual, Arab | E28: Homosexual, Arab, Muslim | F28: Middle Eastern people | G28: Offensive | H28: Offensive | I28: Hate Speech | J28: Hate Speech | K28: GM#5 | L28: GM#1 | M28: Gab | N28: hatespeech | O28: Arab, Homosexual | P28: hatespeech | Q28: African, Homosexual | R28: hatespeech | S28: Arab, Homosexual | T28: =COUNTIF(G28:J28,"*Normal*") -> 0 | U28: =COUNTIF(G28:J28,"*Offensive*") -> 2 | V28: =COUNTIF(G28:J28,"*Hate Speech*") -> 2 | W28: =SUM(T28:V28)/4 -> 1 | X28: =IF(T28>2,"Normal", IF(U28>2, "Offensive", IF(V28>2, "Hate Speech"))) -> FALSE | Y28: =STDEV(T28:V28) -> 1.1547005
A29: 028 | B29: 1178935990074974208_twitter | C29: like literally what the actual fuck i am so mad at this this meme is stupid having nazi and shit but literally says trans fucking niggers this already giving me blackface vibes like this is crossing the line between being a black person | D29: Transgender, Black | E29: Black People | F29: N/A | G29: Normal | H29: Offensive | I29: Hate Speech | J29: Normal | K29: GM#5 | L29: GM#2 | M29: Twitter | N29: normal | O29: None | P29: normal | Q29: African, Homosexual | R29: normal | S29: None | T29: =COUNTIF(G29:J29,"*Normal*") -> 2 | U29: =COUNTIF(G29:J29,"*Offensive*") -> 1 | V29: =COUNTIF(G29:J29,"*Hate Speech*") -> 1 | W29: =SUM(T29:V29)/4 -> 1 | X29: =IF(T29>2,"Normal", IF(U29>2, "Offensive", IF(V29>2, "Hate Speech"))) -> FALSE | Y29: =STDEV(T29:V29) -> 0.57735027
A30: 029 | B30: 1178755558544936966_twitter | C30: <user> <user> she could not be president of the rag head club | D30: Muslim | E30: Arab, Muslim | F30: Muslims | G30: Offensive | H30: Offensive | I30: Hate Speech | J30: Hate Speech | K30: GM#5 | L30: GM#4 | M30: Twitter | N30: offensive | O30: Arab | P30: hatespeech | Q30: Arab | R30: offensive | S30: Hindu | T30: =COUNTIF(G30:J30,"*Normal*") -> 0 | U30: =COUNTIF(G30:J30,"*Offensive*") -> 2 | V30: =COUNTIF(G30:J30,"*Hate Speech*") -> 2 | W30: =SUM(T30:V30)/4 -> 1 | X30: =IF(T30>2,"Normal", IF(U30>2, "Offensive", IF(V30>2, "Hate Speech"))) -> FALSE | Y30: =STDEV(T30:V30) -> 1.1547005
A31: 030 | B31: 9839066_gab | C31: when the muzzies get their sorry shit together and bomb israel i will not feel sorry or shed a tear i will only lament the loss of christian sites and christian lives | D31: Muslim | E31: Muslim people | F31: Muslims, Jewish people | G31: Normal | H31: Offensive | I31: Hate Speech | J31: Hate Speech | K31: GM#5 | L31: GM#3 | M31: Gab | N31: hatespeech | O31: Arab | P31: hatespeech | Q31: Islam | R31: hatespeech | S31: Islam | T31: =COUNTIF(G31:J31,"*Normal*") -> 1 | U31: =COUNTIF(G31:J31,"*Offensive*") -> 1 | V31: =COUNTIF(G31:J31,"*Hate Speech*") -> 2 | W31: =SUM(T31:V31)/4 -> 1 | X31: =IF(T31>2,"Normal", IF(U31>2, "Offensive", IF(V31>2, "Hate Speech"))) -> FALSE | Y31: =STDEV(T31:V31) -> 0.57735027
A32: 031 | B32: 11216949_gab | C32: for my part like jake blues i hate illinois nazis that nice i hate boomer faggots who think it hip to be down with the neegroes the blues man the blues so cool totally not the music of geriatric nigger loving cuck traitors they had sunglasses | D32: Homosexual, African | E32: AfricanBlack, Pro-nazi/nazi | F32: Jewish people, Gay people | G32: Offensive | I32: Hate Speech | J32: Hate Speech | K32: GM#5 | L32: GM#1 | M32: Gab | N32: offensive | O32: Homosexual, African | P32: hatespeech | Q32: Homosexual, African | R32: hatespeech | S32: Homosexual, African | T32: =COUNTIF(G32:J32,"*Normal*") -> 0 | U32: =COUNTIF(G32:J32,"*Offensive*") -> 1 | V32: =COUNTIF(G32:J32,"*Hate Speech*") -> 2 | W32: =SUM(T32:V32)/4 -> 0.75 | X32: =IF(T32>2,"Normal", IF(U32>2, "Offensive", IF(V32>2, "Hate Speech"))) -> FALSE | Y32: =STDEV(T32:V32) -> 1
A33: 032 | B33: 15068033_gab | C33: do not you love when nazi wannabes complain about israel because hey like we do not want them here but we do not want them there either stupidity | D33: Pro-nazi/nazi | E33: Jewish People | F33: N/A | G33: Normal | H33: Normal | I33: Hate Speech | J33: Normal | K33: GM#5 | L33: GM#2 | M33: Gab | N33: offensive | O33: Jewish | P33: normal | Q33: Islam | R33: normal | S33: Men, Women | T33: =COUNTIF(G33:J33,"*Normal*") -> 3 | U33: =COUNTIF(G33:J33,"*Offensive*") -> 0 | V33: =COUNTIF(G33:J33,"*Hate Speech*") -> 1 | W33: =SUM(T33:V33)/4 -> 1 | X33: =IF(T33>2,"Normal", IF(U33>2, "Offensive", IF(V33>2, "Hate Speech"))) -> Normal | Y33: =STDEV(T33:V33) -> 1.5275252
A34: 033 | B34: 1220545521682731008_twitter | C34: <user> <user> remember when you collaborated with neo nazis on a seth rich conspiracy documentary | D34: None | E34: Jewish, Pro-nazi/nazi | F34: N/A | G34: Normal | H34: Normal | I34: Hate Speech | J34: Normal | K34: GM#5 | L34: GM#4 | M34: Twitter | N34: normal | O34: None | P34: normal | Q34: Other | R34: offensive | S34: Other | T34: =COUNTIF(G34:J34,"*Normal*") -> 3 | U34: =COUNTIF(G34:J34,"*Offensive*") -> 0 | V34: =COUNTIF(G34:J34,"*Hate Speech*") -> 1 | W34: =SUM(T34:V34)/4 -> 1 | X34: =IF(T34>2,"Normal", IF(U34>2, "Offensive", IF(V34>2, "Hate Speech"))) -> Normal | Y34: =STDEV(T34:V34) -> 1.5275252
A35: 034 | B35: 1116946053478125571_twitter | C35: then hoes stole my choreo and still managed to make it look bad and lose with it lmfao | D35: Woman | E35: Women | F35: Women | G35: Normal | H35: Normal | I35: Offensive | J35: Offensive | K35: GM#5 | L35: GM#3 | M35: Twitter | N35: offensive | O35: Women | P35: offensive | Q35: Women | R35: offensive | S35: Women | T35: =COUNTIF(G35:J35,"*Normal*") -> 2 | U35: =COUNTIF(G35:J35,"*Offensive*") -> 2 | V35: =COUNTIF(G35:J35,"*Hate Speech*") -> 0 | W35: =SUM(T35:V35)/4 -> 1 | X35: =IF(T35>2,"Normal", IF(U35>2, "Offensive", IF(V35>2, "Hate Speech"))) -> FALSE | Y35: =STDEV(T35:V35) -> 1.1547005
A36: 035 | B36: 19506620_gab | C36: fbi cover up smells of another muzrat terrorist attack | D36: Muslim | E36: Muslim | F36: Muslims | G36: Normal | H36: Offensive | I36: Hate Speech | J36: Hate Speech | K36: GM#5 | L36: GM#1 | M36: Gab | N36: hatespeech | O36: Islam | P36: hatespeech | Q36: Islam | R36: hatespeech | S36: Islam | T36: =COUNTIF(G36:J36,"*Normal*") -> 1 | U36: =COUNTIF(G36:J36,"*Offensive*") -> 1 | V36: =COUNTIF(G36:J36,"*Hate Speech*") -> 2 | W36: =SUM(T36:V36)/4 -> 1 | X36: =IF(T36>2,"Normal", IF(U36>2, "Offensive", IF(V36>2, "Hate Speech"))) -> FALSE | Y36: =STDEV(T36:V36) -> 0.57735027
A37: 036 | B37: 1179035441854443520_twitter | C37: white devils like it i am drinking coffee brought to me by white devils sidekicks | D37: Causasian | E37: White People | F37: White people | G37: Normal | H37: Normal | I37: Hate Speech | J37: Offensive | K37: GM#5 | L37: GM#2 | M37: Twitter | N37: hatespeech | O37: Caucasian | P37: normal | Q37: None | R37: hatespeech | S37: Caucasian | T37: =COUNTIF(G37:J37,"*Normal*") -> 2 | U37: =COUNTIF(G37:J37,"*Offensive*") -> 1 | V37: =COUNTIF(G37:J37,"*Hate Speech*") -> 1 | W37: =SUM(T37:V37)/4 -> 1 | X37: =IF(T37>2,"Normal", IF(U37>2, "Offensive", IF(V37>2, "Hate Speech"))) -> FALSE | Y37: =STDEV(T37:V37) -> 0.57735027
A38: 037 | B38: 1211743854401064961_twitter | C38: i didn ’ t get a pedicure last rome i got my nails done n now my feet look brazy this is ghetto | D38: African | E38: AfricanBlack | F38: N/A | G38: Normal | H38: Offensive | I38: Offensive | J38: Normal | K38: GM#5 | L38: GM#4 | M38: Twitter | N38: offensive | O38: Other | P38: offensive | Q38: None | R38: normal | S38: Other | T38: =COUNTIF(G38:J38,"*Normal*") -> 2 | U38: =COUNTIF(G38:J38,"*Offensive*") -> 2 | V38: =COUNTIF(G38:J38,"*Hate Speech*") -> 0 | W38: =SUM(T38:V38)/4 -> 1 | X38: =IF(T38>2,"Normal", IF(U38>2, "Offensive", IF(V38>2, "Hate Speech"))) -> FALSE | Y38: =STDEV(T38:V38) -> 1.1547005
A39: 038 | B39: 13567394_gab | C39: this coons constituents voted for her just to get her out of their district they were embarrassed by her so they took out the trash | D39: None | E39: Black people | F39: Black people | G39: Offensive | H39: Normal | I39: Hate Speech | J39: Hate Speech | K39: GM#5 | L39: GM#3 | M39: Gab | N39: hatespeech | O39: African, Women | P39: offensive | Q39: African | R39: hatespeech | S39: African | T39: =COUNTIF(G39:J39,"*Normal*") -> 1 | U39: =COUNTIF(G39:J39,"*Offensive*") -> 1 | V39: =COUNTIF(G39:J39,"*Hate Speech*") -> 2 | W39: =SUM(T39:V39)/4 -> 1 | X39: =IF(T39>2,"Normal", IF(U39>2, "Offensive", IF(V39>2, "Hate Speech"))) -> FALSE | Y39: =STDEV(T39:V39) -> 0.57735027
A40: 039 | B40: 26510414_gab | C40: i think we are past the negotiation phase it time to issue an ultimatum all sand niggers and kikes out of america or get executed an invader | D40: Arab, Jewish | E40: AfricanBlack, Arab, Muslim, Jewish | F40: Middle Eastern people, Jewish people | G40: Hate Speech | H40: Hate Speech | I40: Hate Speech | J40: Hate Speech | K40: GM#5 | L40: GM#1 | M40: Gab | N40: hatespeech | O40: Arab, Jewish, Refugee | P40: hatespeech | Q40: Arab, Islam | R40: hatespeech | S40: Arab, Jewish | T40: =COUNTIF(G40:J40,"*Normal*") -> 0 | U40: =COUNTIF(G40:J40,"*Offensive*") -> 0 | V40: =COUNTIF(G40:J40,"*Hate Speech*") -> 4 | W40: =SUM(T40:V40)/4 -> 1 | X40: =IF(T40>2,"Normal", IF(U40>2, "Offensive", IF(V40>2, "Hate Speech"))) -> Hate Speech | Y40: =STDEV(T40:V40) -> 2.3094011
A41: 040 | B41: 1165679759755530243_twitter | C41: we really finna elect biden with the appalling amount of rapey advances he made on camera with literal children damn lmfao | D41: None | E41: Women (implied minors) | F41: Women, Children | G41: Normal | H41: Normal | I41: Offensive | J41: Offensive | K41: GM#5 | L41: GM#2 | M41: Twitter | N41: normal | O41: None | P41: normal | Q41: None | R41: normal | S41: None | T41: =COUNTIF(G41:J41,"*Normal*") -> 2 | U41: =COUNTIF(G41:J41,"*Offensive*") -> 2 | V41: =COUNTIF(G41:J41,"*Hate Speech*") -> 0 | W41: =SUM(T41:V41)/4 -> 1 | X41: =IF(T41>2,"Normal", IF(U41>2, "Offensive", IF(V41>2, "Hate Speech"))) -> FALSE | Y41: =STDEV(T41:V41) -> 1.1547005
A42: 041 | B42: 1179084859832180736_twitter | C42: i just thought about wtf i am doing and i am fucking retarded | D42: None | E42: Disability | F42: People with disabilities | G42: Normal | H42: Normal | I42: Offensive | J42: Offensive | K42: GM#5 | L42: GM#4 | M42: Twitter | N42: normal | O42: Other | P42: normal | Q42: None | R42: hatespeech | S42: Disability | T42: =COUNTIF(G42:J42,"*Normal*") -> 2 | U42: =COUNTIF(G42:J42,"*Offensive*") -> 2 | V42: =COUNTIF(G42:J42,"*Hate Speech*") -> 0 | W42: =SUM(T42:V42)/4 -> 1 | X42: =IF(T42>2,"Normal", IF(U42>2, "Offensive", IF(V42>2, "Hate Speech"))) -> FALSE | Y42: =STDEV(T42:V42) -> 1.1547005
A43: 042 | B43: 21605385_gab | C43: also benefits outed taxpayers money being spent on these inbreed moslem shite depleting monies available for nationals of this country and every country they inbreed in | D43: Muslim | E43: Muslim people | F43: Muslims | G43: Offensive | H43: Offensive | I43: Hate Speech | J43: Hate Speech | K43: GM#5 | L43: GM#3 | M43: Gab | N43: normal | O43: None | P43: hatespeech | Q43: Minority, Islam | R43: hatespeech | S43: Refugee, Islam | T43: =COUNTIF(G43:J43,"*Normal*") -> 0 | U43: =COUNTIF(G43:J43,"*Offensive*") -> 2 | V43: =COUNTIF(G43:J43,"*Hate Speech*") -> 2 | W43: =SUM(T43:V43)/4 -> 1 | X43: =IF(T43>2,"Normal", IF(U43>2, "Offensive", IF(V43>2, "Hate Speech"))) -> FALSE | Y43: =STDEV(T43:V43) -> 1.1547005
A44: 043 | B44: 1177971370896039936_twitter | C44: niggers should suck white dick them faggots | D44: Black, Homosexual | E44: AfricanBlack, Homosexual | F44: Black people, Gay people | G44: Offensive | H44: Hate Speech | I44: Hate Speech | J44: Hate Speech | K44: GM#5 | L44: GM#1 | M44: Twitter | N44: hatespeech | O44: African, Homosexual | P44: hatespeech | Q44: African | R44: hatespeech | S44: African, Homosexual | T44: =COUNTIF(G44:J44,"*Normal*") -> 0 | U44: =COUNTIF(G44:J44,"*Offensive*") -> 1 | V44: =COUNTIF(G44:J44,"*Hate Speech*") -> 3 | W44: =SUM(T44:V44)/4 -> 1 | X44: =IF(T44>2,"Normal", IF(U44>2, "Offensive", IF(V44>2, "Hate Speech"))) -> Hate Speech | Y44: =STDEV(T44:V44) -> 1.5275252
... A59: 058 | B59: 16723301_gab | C59: the fat nigger has tits on her back and pubes growing out of her hayid 🙈 | D59: African | E59: Black women | F59: Black women | G59: Offensive | H59: Offensive | I59: Hate Speech | J59: Hate Speech | K59: GM#5 | L59: GM#3 | M59: Gab | N59: hatespeech | O59: African | P59: hatespeech | Q59: African | R59: hatespeech | S59: Other, African, Women | T59: =COUNTIF(G59:J59,"*Normal*") -> 0 | U59: =COUNTIF(G59:J59,"*Offensive*") -> 2 | V59: =COUNTIF(G59:J59,"*Hate Speech*") -> 2 | W59: =SUM(T59:V59)/4 -> 1 | X59: =IF(T59>2,"Normal", IF(U59>2, "Offensive", IF(V59>2, "Hate Speech"))) -> FALSE | Y59: =STDEV(T59:V59) -> 1.1547005
A60: 059 | B60: 20838853_gab | C60: i am wondering why asian people are not offended that they are describing middle eastern goat fucking muslimes as asians in the uk | D60: Arab | E60: Muslim, ChineseAsian | F60: Muslims, Middle Eastern people | G60: Offensive | I60: Hate Speech | J60: Hate Speech | K60: GM#5 | L60: GM#1 | M60: Gab | N60: normal | O60: None | P60: hatespeech | Q60: Islam | R60: hatespeech | S60: Asian, Islam | T60: =COUNTIF(G60:J60,"*Normal*") -> 0 | U60: =COUNTIF(G60:J60,"*Offensive*") -> 1 | V60: =COUNTIF(G60:J60,"*Hate Speech*") -> 2 | W60: =SUM(T60:V60)/4 -> 0.75 | X60: =IF(T60>2,"Normal", IF(U60>2, "Offensive", IF(V60>2, "Hate Speech"))) -> FALSE | Y60: =STDEV(T60:V60) -> 1
A61: 060 | B61: 1258692523603746816_twitter | C61: it be the same hoes talking shit in a group chat that ’ insecure asf in real life by themselves 😭 | D61: Woman | E61: Women | F61: N/A | G61: Normal | H61: Normal | I61: Offensive | J61: Normal | K61: GM#5 | L61: GM#2 | M61: Twitter | N61: offensive | O61: None | P61: offensive | Q61: None | R61: offensive | S61: Women | T61: =COUNTIF(G61:J61,"*Normal*") -> 3 | U61: =COUNTIF(G61:J61,"*Offensive*") -> 1 | V61: =COUNTIF(G61:J61,"*Hate Speech*") -> 0 | W61: =SUM(T61:V61)/4 -> 1 | X61: =IF(T61>2,"Normal", IF(U61>2, "Offensive", IF(V61>2, "Hate Speech"))) -> Normal | Y61: =STDEV(T61:V61) -> 1.5275252
A62: 061 | B62: 11174183_gab | C62: just what we need a sandnigger goatfucker for governor ffs | D62: Arab | E62: Muslim, Arab | F62: Black people, Muslims | G62: Offensive | H62: Offensive | I62: Hate Speech | J62: Hate Speech | K62: GM#5 | L62: GM#4 | M62: Gab | N62: hatespeech | O62: Arab, Islam | P62: hatespeech | Q62: Arab | R62: hatespeech | S62: Arab, Islam | T62: =COUNTIF(G62:J62,"*Normal*") -> 0 | U62: =COUNTIF(G62:J62,"*Offensive*") -> 2 | V62: =COUNTIF(G62:J62,"*Hate Speech*") -> 2 | W62: =SUM(T62:V62)/4 -> 1 | X62: =IF(T62>2,"Normal", IF(U62>2, "Offensive", IF(V62>2, "Hate Speech"))) -> FALSE | Y62: =STDEV(T62:V62) -> 1.1547005
A63: 062 | B63: 27392816_gab | C63: the sand niggers deserve the same | D63: Arab | E63: Arab/Muslim people | F63: Middle Eastern people | G63: Offensive | H63: Offensive | I63: Hate Speech | J63: Hate Speech | K63: GM#5 | L63: GM#3 | M63: Gab | N63: hatespeech | O63: Arab | P63: hatespeech | Q63: Arab | R63: hatespeech | S63: Arab | T63: =COUNTIF(G63:J63,"*Normal*") -> 0 | U63: =COUNTIF(G63:J63,"*Offensive*") -> 2 | V63: =COUNTIF(G63:J63,"*Hate Speech*") -> 2 | W63: =SUM(T63:V63)/4 -> 1 | X63: =IF(T63>2,"Normal", IF(U63>2, "Offensive", IF(V63>2, "Hate Speech"))) -> FALSE | Y63: =STDEV(T63:V63) -> 1.1547005
A64: 063 | B64: 18913134_gab | C64: for crying out loud millions if children are abused mentally ohydically emotionally are raped sexually abused every day do you want more | D64: None | E64: Victims of SA | F64: N/A | G64: Normal | H64: Normal | I64: Normal | J64: Normal | K64: GM#5 | L64: GM#1 | M64: Gab | N64: normal | O64: None | P64: normal | Q64: Other | R64: offensive | S64: None | T64: =COUNTIF(G64:J64,"*Normal*") -> 4 | U64: =COUNTIF(G64:J64,"*Offensive*") -> 0 | V64: =COUNTIF(G64:J64,"*Hate Speech*") -> 0 | W64: =SUM(T64:V64)/4 -> 1 | X64: =IF(T64>2,"Normal", IF(U64>2, "Offensive", IF(V64>2, "Hate Speech"))) -> Normal | Y64: =STDEV(T64:V64) -> 2.3094011
A65: 064 | B65: 1198265466889785344_twitter | C65: single life is very ghetto | D65: Economic Status Status | E65: Black People (cultural stereotype) | F65: N/A | G65: Normal | H65: Normal | I65: Offensive | J65: Normal | K65: GM#5 | L65: GM#2 | M65: Twitter | N65: normal | O65: None | P65: normal | Q65: None | R65: normal | S65: None | T65: =COUNTIF(G65:J65,"*Normal*") -> 3 | U65: =COUNTIF(G65:J65,"*Offensive*") -> 1 | V65: =COUNTIF(G65:J65,"*Hate Speech*") -> 0 | W65: =SUM(T65:V65)/4 -> 1 | X65: =IF(T65>2,"Normal", IF(U65>2, "Offensive", IF(V65>2, "Hate Speech"))) -> Normal | Y65: =STDEV(T65:V65) -> 1.5275252
A66: 065 | B66: 1089693014132441088_twitter | C66: a buddy cop show where one of them is a holocaust survivor and the other is a holocaust denier | D66: None | E66: Jewish | F66: N/A | G66: Normal | H66: Normal | I66: Offensive | J66: Normal | K66: GM#5 | L66: GM#4 | M66: Twitter | N66: normal | O66: Jewish, Other | P66: normal | Q66: Other | R66: offensive | S66: Other | T66: =COUNTIF(G66:J66,"*Normal*") -> 3 | U66: =COUNTIF(G66:J66,"*Offensive*") -> 1 | V66: =COUNTIF(G66:J66,"*Hate Speech*") -> 0 | W66: =SUM(T66:V66)/4 -> 1 | X66: =IF(T66>2,"Normal", IF(U66>2, "Offensive", IF(V66>2, "Hate Speech"))) -> Normal | Y66: =STDEV(T66:V66) -> 1.5275252
A67: 066 | B67: 18710576_gab | C67: if you have a daughter will you name her sandy you know as in sand nigger | D67: Arab | E67: Arab/Muslim people | F67: Middle Eastern people | G67: Offensive | H67: Offensive | I67: Hate Speech | J67: Hate Speech | K67: GM#5 | L67: GM#3 | M67: Gab | N67: hatespeech | O67: Arab, Islam | P67: offensive | Q67: Arab, Other | R67: hatespeech | S67: Arab | T67: =COUNTIF(G67:J67,"*Normal*") -> 0 | U67: =COUNTIF(G67:J67,"*Offensive*") -> 2 | V67: =COUNTIF(G67:J67,"*Hate Speech*") -> 2 | W67: =SUM(T67:V67)/4 -> 1 | X67: =IF(T67>2,"Normal", IF(U67>2, "Offensive", IF(V67>2, "Hate Speech"))) -> FALSE | Y67: =STDEV(T67:V67) -> 1.1547005
A68: 067 | B68: 15843155_gab | C68: i am still sad i have been trying to make my phone work so it will take pictures the rooftops are all white in my neighborhood and it so lovely i hate my phone right now | D68: None | F68: N/A | G68: Normal | H68: Normal | I68: Normal | J68: Normal | K68: GM#5 | L68: GM#1 | M68: Gab | N68: normal | O68: None | P68: normal | Q68: None | R68: offensive | S68: African, Arab, Asian, Hispanic | T68: =COUNTIF(G68:J68,"*Normal*") -> 4 | U68: =COUNTIF(G68:J68,"*Offensive*") -> 0 | V68: =COUNTIF(G68:J68,"*Hate Speech*") -> 0 | W68: =SUM(T68:V68)/4 -> 1 | X68: =IF(T68>2,"Normal", IF(U68>2, "Offensive", IF(V68>2, "Hate Speech"))) -> Normal | Y68: =STDEV(T68:V68) -> 2.3094011
A69: 068 | B69: 16154028_gab | C69: still avoiding my questions i see castrato what do you have against people hating the marxist cultural agenda led by your beloved jews who also lead the homosexual movement which you apparently support is it because you are a faggoty posin person masquerading as a christian | D69: Homosexual, Jewish, | E69: Jewish People, LGBTQ+ | F69: N/A | G69: Offensive | H69: Offensive | I69: Hate Speech | J69: Normal | K69: GM#5 | L69: GM#2 | M69: Gab | N69: offensive | O69: Homosexual, Jewish | P69: offensive | Q69: Homosexual, Christian, Jewish, Other | R69: offensive | S69: Homosexual, Jewish | T69: =COUNTIF(G69:J69,"*Normal*") -> 1 | U69: =COUNTIF(G69:J69,"*Offensive*") -> 2 | V69: =COUNTIF(G69:J69,"*Hate Speech*") -> 1 | W69: =SUM(T69:V69)/4 -> 1 | X69: =IF(T69>2,"Normal", IF(U69>2, "Offensive", IF(V69>2, "Hate Speech"))) -> FALSE | Y69: =STDEV(T69:V69) -> 0.57735027
A70: 069 | B70: 1079397452887834624_twitter | C70: <user> <user> not bad idea but they are retardet | D70: None | E70: Disability | F70: People with disabilities | G70: Offensive | H70: Normal | I70: Offensive | J70: Offensive | K70: GM#5 | L70: GM#4 | M70: Twitter | N70: offensive | O70: None | P70: offensive | Q70: None | R70: offensive | S70: Other | T70: =COUNTIF(G70:J70,"*Normal*") -> 1 | U70: =COUNTIF(G70:J70,"*Offensive*") -> 3 | V70: =COUNTIF(G70:J70,"*Hate Speech*") -> 0 | W70: =SUM(T70:V70)/4 -> 1 | X70: =IF(T70>2,"Normal", IF(U70>2, "Offensive", IF(V70>2, "Hate Speech"))) -> Offensive | Y70: =STDEV(T70:V70) -> 1.5275252
A71: 070 | B71: 5244548_gab | C71: you know it a sad state of affairs living in england when even the immigrants are getting pissed off with immigration | D71: Immigrant | E71: - | F71: N/A | G71: Normal | H71: Normal | I71: Normal | J71: Normal | K71: GM#5 | L71: GM#3 | M71: Gab | N71: offensive | O71: Refugee | P71: offensive | Q71: Refugee | R71: offensive | S71: Refugee | T71: =COUNTIF(G71:J71,"*Normal*") -> 4 | U71: =COUNTIF(G71:J71,"*Offensive*") -> 0 | V71: =COUNTIF(G71:J71,"*Hate Speech*") -> 0 | W71: =SUM(T71:V71)/4 -> 1 | X71: =IF(T71>2,"Normal", IF(U71>2, "Offensive", IF(V71>2, "Hate Speech"))) -> Normal | Y71: =STDEV(T71:V71) -> 2.3094011
A72: 071 | B72: 18362047_gab | C72: agreed public shaming is usually enough to keep faggots in the closet anyway | D72: Homosexual | E72: Homosexual | F72: Gay people | G72: Offensive | H72: Hate Speech | I72: Offensive | J72: Hate Speech | K72: GM#5 | L72: GM#1 | M72: Gab | N72: offensive | O72: Homosexual | P72: hatespeech | Q72: Homosexual | R72: hatespeech | S72: Homosexual | T72: =COUNTIF(G72:J72,"*Normal*") -> 0 | U72: =COUNTIF(G72:J72,"*Offensive*") -> 2 | V72: =COUNTIF(G72:J72,"*Hate Speech*") -> 2 | W72: =SUM(T72:V72)/4 -> 1 | X72: =IF(T72>2,"Normal", IF(U72>2, "Offensive", IF(V72>2, "Hate Speech"))) -> FALSE | Y72: =STDEV(T72:V72) -> 1.1547005
A73: 072 | B73: 11538998_gab | C73: america is an example of ethnic groups interacting with one another in peace now if we could just get the democratic marxists to let black people off the ghetto plantation we might be able to get things cleaned up | D73: African | E73: Black People | F73: N/A | G73: Offensive | H73: Normal | I73: Hate Speech | J73: Normal | K73: GM#5 | L73: GM#2 | M73: Gab | N73: hatespeech | O73: African | P73: offensive | Q73: African | R73: offensive | S73: African | T73: =COUNTIF(G73:J73,"*Normal*") -> 2 | U73: =COUNTIF(G73:J73,"*Offensive*") -> 1 | V73: =COUNTIF(G73:J73,"*Hate Speech*") -> 1 | W73: =SUM(T73:V73)/4 -> 1 | X73: =IF(T73>2,"Normal", IF(U73>2, "Offensive", IF(V73>2, "Hate Speech"))) -> FALSE | Y73: =STDEV(T73:V73) -> 0.57735027
A74: 073 | B74: 1146254885148479489_twitter | C74: <user> kash sulla meat dishes look garbage amp are served as if you are feeding refugees | D74: Refugee | E74: Immigrant, Refugee | F74: Refugees | G74: Offensive | H74: Offensive | I74: Offensive | J74: Offensive | K74: GM#5 | L74: GM#4 | M74: Twitter | N74: offensive | O74: Refugee | P74: offensive | Q74: Refugee | R74: normal | S74: None | T74: =COUNTIF(G74:J74,"*Normal*") -> 0 | U74: =COUNTIF(G74:J74,"*Offensive*") -> 4 | V74: =COUNTIF(G74:J74,"*Hate Speech*") -> 0 | W74: =SUM(T74:V74)/4 -> 1 | X74: =IF(T74>2,"Normal", IF(U74>2, "Offensive", IF(V74>2, "Hate Speech"))) -> Offensive | Y74: =STDEV(T74:V74) -> 2.3094011
A75: 074 | B75: 19410887_gab | C75: fuck you kike | D75: Jewish | E75: Jewish people | F75: Jewish people | G75: Offensive | H75: Offensive | I75: Hate Speech | J75: Hate Speech | K75: GM#5 | L75: GM#3 | M75: Gab | N75: hatespeech | O75: Jewish | P75: hatespeech | Q75: Jewish | R75: hatespeech | S75: Jewish | T75: =COUNTIF(G75:J75,"*Normal*") -> 0 | U75: =COUNTIF(G75:J75,"*Offensive*") -> 2 | V75: =COUNTIF(G75:J75,"*Hate Speech*") -> 2 | W75: =SUM(T75:V75)/4 -> 1 | X75: =IF(T75>2,"Normal", IF(U75>2, "Offensive", IF(V75>2, "Hate Speech"))) -> FALSE | Y75: =STDEV(T75:V75) -> 1.1547005
A76: 075 | B76: 23814770_gab | C76: only shit gay bout me in the shit i shit out in da toiket bowl you queers wanna suck on my shit covered asshole son | D76: Homosexual | E76: Homosexual, Queer | F76: Gay people | G76: Offensive | H76: Offensive | I76: Offensive | J76: Hate Speech | K76: GM#5 | L76: GM#1 | M76: Gab | N76: hatespeech | O76: Homosexual | P76: offensive | Q76: Homosexual | R76: offensive | S76: Homosexual | T76: =COUNTIF(G76:J76,"*Normal*") -> 0 | U76: =COUNTIF(G76:J76,"*Offensive*") -> 3 | V76: =COUNTIF(G76:J76,"*Hate Speech*") -> 1 | W76: =SUM(T76:V76)/4 -> 1 | X76: =IF(T76>2,"Normal", IF(U76>2, "Offensive", IF(V76>2, "Hate Speech"))) -> Offensive | Y76: =STDEV(T76:V76) -> 1.5275252
A77: 076 | B77: 1179085774526042113_twitter | C77: <user> <number> years there was a belgian pedophilia who went to jail with his wife his partner in crime idk if it the right word bc kidnapped <number> girls raped and let them die in his cellar and his partner in crime is now free | D77: None | E77: Women (minors) | F77: N/A | G77: Normal | H77: Normal | I77: Normal | J77: Normal | K77: GM#5 | L77: GM#2 | M77: Twitter | N77: normal | O77: None | P77: normal | Q77: None | R77: normal | S77: None | T77: =COUNTIF(G77:J77,"*Normal*") -> 4 | U77: =COUNTIF(G77:J77,"*Offensive*") -> 0 | V77: =COUNTIF(G77:J77,"*Hate Speech*") -> 0 | W77: =SUM(T77:V77)/4 -> 1 | X77: =IF(T77>2,"Normal", IF(U77>2, "Offensive", IF(V77>2, "Hate Speech"))) -> Normal | Y77: =STDEV(T77:V77) -> 2.3094011
A78: 077 | B78: 17656169_gab | C78: something the world of wildlife has not allowed to shoot white rhinos for instance unless of course you are a billionare elite but even then you d have to do it in secret | D78: None | F78: N/A | G78: Normal | H78: Normal | I78: Normal | J78: Normal | K78: GM#5 | L78: GM#4 | M78: Gab | N78: normal | O78: None | P78: normal | Q78: None | R78: normal | S78: Other | T78: =COUNTIF(G78:J78,"*Normal*") -> 4 | U78: =COUNTIF(G78:J78,"*Offensive*") -> 0 | V78: =COUNTIF(G78:J78,"*Hate Speech*") -> 0 | W78: =SUM(T78:V78)/4 -> 1 | X78: =IF(T78>2,"Normal", IF(U78>2, "Offensive", IF(V78>2, "Hate Speech"))) -> Normal | Y78: =STDEV(T78:V78) -> 2.3094011
A79: 078 | B79: 8042374_gab | C79: fuckmanchester british men are too scared to even talk about it let alone do anything about it they let their daughters be raped and killed and do not make a peep like scared little mice they are not men they are cowards shameful lowly cowards | D79: None | E79: Muslim people | F79: Muslims | G79: Normal | H79: Offensive | I79: Hate Speech | J79: Hate Speech | K79: GM#5 | L79: GM#3 | M79: Gab | N79: offensive | O79: Other | P79: hatespeech | Q79: Men, Refugee | R79: hatespeech | S79: Caucasian | T79: =COUNTIF(G79:J79,"*Normal*") -> 1 | U79: =COUNTIF(G79:J79,"*Offensive*") -> 1 | V79: =COUNTIF(G79:J79,"*Hate Speech*") -> 2 | W79: =SUM(T79:V79)/4 -> 1 | X79: =IF(T79>2,"Normal", IF(U79>2, "Offensive", IF(V79>2, "Hate Speech"))) -> FALSE | Y79: =STDEV(T79:V79) -> 0.57735027
A80: 079 | B80: 14262039_gab | C80: nah baldwin might be making a good point here i have no love for the kike weinstein or the thots who whored themselves for money but baldwin can let the feminists and jews bash him for a while might redpill him and flip him from being a libtard | D80: Jewish, Woman, Liberal | E80: Jewish, Woman | F80: Women, Jewish people | G80: Offensive | H80: Offensive | I80: Hate Speech | J80: Offensive | K80: GM#5 | L80: GM#1 | M80: Gab | N80: hatespeech | O80: Women, Jewish | P80: hatespeech | Q80: Women, Jewish | R80: hatespeech | S80: Women, Jewish | T80: =COUNTIF(G80:J80,"*Normal*") -> 0 | U80: =COUNTIF(G80:J80,"*Offensive*") -> 3 | V80: =COUNTIF(G80:J80,"*Hate Speech*") -> 1 | W80: =SUM(T80:V80)/4 -> 1 | X80: =IF(T80>2,"Normal", IF(U80>2, "Offensive", IF(V80>2, "Hate Speech"))) -> Offensive | Y80: =STDEV(T80:V80) -> 1.5275252
A81: 080 | B81: 22346132_gab | C81: research finds more than half of london lgbtq pubs clubs and music venues have closed since <number> i can not say i am surprised with the rise of islam in the capital and so many queers dying of aids | D81: Homosexual, Muslim | E81: Muslim People | F81: N/A | G81: Normal | H81: Normal | I81: Hate Speech | J81: Normal | K81: GM#5 | L81: GM#2 | M81: Gab | N81: normal | O81: None | P81: offensive | Q81: Islam, Homosexual | R81: offensive | S81: Homosexual | T81: =COUNTIF(G81:J81,"*Normal*") -> 3 | U81: =COUNTIF(G81:J81,"*Offensive*") -> 0 | V81: =COUNTIF(G81:J81,"*Hate Speech*") -> 1 | W81: =SUM(T81:V81)/4 -> 1 | X81: =IF(T81>2,"Normal", IF(U81>2, "Offensive", IF(V81>2, "Hate Speech"))) -> Normal | Y81: =STDEV(T81:V81) -> 1.5275252
A82: 081 | B82: 15841729_gab | C82: having a retarded child is winning the sympathy lottery now you have your own retarded screaming lump of meat you can parade around for gibs and attention it a lifelong virtual signalling act that pays dividends | D82: Disability | E82: Disability | F82: People with disabilities | G82: Offensive | H82: Offensive | I82: Offensive | J82: Hate Speech | K82: GM#5 | L82: GM#4 | M82: Gab | N82: offensive | O82: Other | P82: normal | Q82: None | R82: offensive | S82: Other | T82: =COUNTIF(G82:J82,"*Normal*") -> 0 | U82: =COUNTIF(G82:J82,"*Offensive*") -> 3 | V82: =COUNTIF(G82:J82,"*Hate Speech*") -> 1 | W82: =SUM(T82:V82)/4 -> 1 | X82: =IF(T82>2,"Normal", IF(U82>2, "Offensive", IF(V82>2, "Hate Speech"))) -> Offensive | Y82: =STDEV(T82:V82) -> 1.5275252
A83: 082 | B83: 7547439_gab | C83: during the 4 0 quota of immigrants were established expanding into the 5 0 every <number> years until the internal security act required aliens to report their addresses the immigration nationality act in <number> tightened screening restriction preferences <number> skilled workers that excluded communists | D83: Immigrant | E83: - | F83: N/A | G83: Normal | H83: Normal | I83: Normal | J83: Normal | K83: GM#5 | L83: GM#3 | M83: Gab | N83: normal | O83: Refugee | P83: normal | Q83: Refugee | R83: normal | S83: None | T83: =COUNTIF(G83:J83,"*Normal*") -> 4 | U83: =COUNTIF(G83:J83,"*Offensive*") -> 0 | V83: =COUNTIF(G83:J83,"*Hate Speech*") -> 0 | W83: =SUM(T83:V83)/4 -> 1 | X83: =IF(T83>2,"Normal", IF(U83>2, "Offensive", IF(V83>2, "Hate Speech"))) -> Normal | Y83: =STDEV(T83:V83) -> 2.3094011
A84: 083 | B84: 20614405_gab | C84: yep they have become the party representing muslims blacks asians queers and any other undesirable element in our society not the working man they have taken this once great country well and truly down the toilet sorry to say but it has become a shit hole | D84: Muslim, African, Asian, Homosexual | E84: Muslim, AfricanBlack, ChineseAsian, Homosexual, Queer | F84: Immigrants, Ethnic minorities | G84: Offensive | H84: Hate Speech | I84: Hate Speech | J84: Hate Speech | K84: GM#5 | L84: GM#1 | M84: Gab | N84: hatespeech | O84: African, Asian, Caucasian | P84: hatespeech | Q84: Homosexual, African, Arab, Asian, Islam | R84: offensive | S84: Homosexual, African, Asian, Islam | T84: =COUNTIF(G84:J84,"*Normal*") -> 0 | U84: =COUNTIF(G84:J84,"*Offensive*") -> 1 | V84: =COUNTIF(G84:J84,"*Hate Speech*") -> 3 | W84: =SUM(T84:V84)/4 -> 1 | X84: =IF(T84>2,"Normal", IF(U84>2, "Offensive", IF(V84>2, "Hate Speech"))) -> Hate Speech | Y84: =STDEV(T84:V84) -> 1.5275252
A85: 084 | B85: 1178904752689762304_twitter | C85: <user> yeah kiss my skinny white ass september 🍁 | D85: None | E85: White People | F85: N/A | G85: Normal | H85: Normal | I85: Offensive | J85: Normal | K85: GM#5 | L85: GM#2 | M85: Twitter | N85: normal | O85: None | P85: normal | Q85: None | R85: normal | S85: None | T85: =COUNTIF(G85:J85,"*Normal*") -> 3 | U85: =COUNTIF(G85:J85,"*Offensive*") -> 1 | V85: =COUNTIF(G85:J85,"*Hate Speech*") -> 0 | W85: =SUM(T85:V85)/4 -> 1 | X85: =IF(T85>2,"Normal", IF(U85>2, "Offensive", IF(V85>2, "Hate Speech"))) -> Normal | Y85: =STDEV(T85:V85) -> 1.5275252
A86: 085 | B86: 22500099_gab | C86: the koran says the only way a gay moslem can get to paradise is by killing infidels those infidels you kill will be your slaves in the afterlife so thankfully he preferred brown men as several survivors claimed to have slept with him | D86: Muslim | E86: Muslim, Homosexual | F86: Muslims, Non-Muslims | G86: Offensive | H86: Offensive | I86: Hate Speech | J86: Hate Speech | K86: GM#5 | L86: GM#4 | M86: Gab | N86: normal | O86: None | P86: offensive | Q86: Islam, Homosexual | R86: offensive | S86: Islam | T86: =COUNTIF(G86:J86,"*Normal*") -> 0 | U86: =COUNTIF(G86:J86,"*Offensive*") -> 2 | V86: =COUNTIF(G86:J86,"*Hate Speech*") -> 2 | W86: =SUM(T86:V86)/4 -> 1 | X86: =IF(T86>2,"Normal", IF(U86>2, "Offensive", IF(V86>2, "Hate Speech"))) -> FALSE | Y86: =STDEV(T86:V86) -> 1.1547005
A87: 086 | B87: 19526192_gab | C87: go sleep you old whore go get raped by a muslim you will enjoy it | D87: Muslim, Woman | E87: Women, Muslim people | F87: Muslims, Women | G87: Hate Speech | H87: Hate Speech | I87: Hate Speech | J87: Hate Speech | K87: GM#5 | L87: GM#3 | M87: Gab | N87: hatespeech | O87: Islam, Women | P87: hatespeech | Q87: Islam, Women, Other | R87: hatespeech | S87: Arab, Islam, Men, Women | T87: =COUNTIF(G87:J87,"*Normal*") -> 0 | U87: =COUNTIF(G87:J87,"*Offensive*") -> 0 | V87: =COUNTIF(G87:J87,"*Hate Speech*") -> 4 | W87: =SUM(T87:V87)/4 -> 1 | X87: =IF(T87>2,"Normal", IF(U87>2, "Offensive", IF(V87>2, "Hate Speech"))) -> Hate Speech | Y87: =STDEV(T87:V87) -> 2.3094011
A88: 087 | B88: 1178323077282897920_twitter | C88: there something about a stage full of white women bopping along to lizzo after watching a show of mediocre performances by said white women that just affirms we need more representation and we need it now wanna do burlesque wanna do drag get at me | D88: Woman | E88: Caucasian, Woman | F88: Black people | G88: Normal | H88: Normal | I88: Offensive | J88: Offensive | K88: GM#5 | L88: GM#1 | M88: Twitter | N88: normal | O88: None | P88: normal | Q88: None | R88: normal | S88: Caucasian | T88: =COUNTIF(G88:J88,"*Normal*") -> 2 | U88: =COUNTIF(G88:J88,"*Offensive*") -> 2 | V88: =COUNTIF(G88:J88,"*Hate Speech*") -> 0 | W88: =SUM(T88:V88)/4 -> 1 | X88: =IF(T88>2,"Normal", IF(U88>2, "Offensive", IF(V88>2, "Hate Speech"))) -> FALSE | Y88: =STDEV(T88:V88) -> 1.1547005
A89: 088 | B89: 1166190318116646912_twitter | C89: adulthood is the most ghetto hood i ’ ve ever been in bitch i hate it here | D89: None | E89: Black People (cultural) | F89: N/A | G89: Normal | H89: Normal | I89: Offensive | J89: Normal | K89: GM#5 | L89: GM#2 | M89: Twitter | N89: offensive | O89: African | P89: hatespeech | Q89: None | R89: normal | S89: None | T89: =COUNTIF(G89:J89,"*Normal*") -> 3 | U89: =COUNTIF(G89:J89,"*Offensive*") -> 1 | V89: =COUNTIF(G89:J89,"*Hate Speech*") -> 0 | W89: =SUM(T89:V89)/4 -> 1 | X89: =IF(T89>2,"Normal", IF(U89>2, "Offensive", IF(V89>2, "Hate Speech"))) -> Normal | Y89: =STDEV(T89:V89) -> 1.5275252
A90: 089 | B90: 1225661082083024897_twitter | C90: caucasians wearing masks to prevent coronavirus and still don ’ t wash their hands | D90: CaucAsian | E90: Caucasian | F90: N/A | G90: Normal | H90: Offensive | I90: Offensive | J90: Normal | K90: GM#5 | L90: GM#4 | M90: Twitter | N90: normal | O90: Caucasian | P90: offensive | Q90: Caucasian | R90: normal | S90: Caucasian | T90: =COUNTIF(G90:J90,"*Normal*") -> 2 | U90: =COUNTIF(G90:J90,"*Offensive*") -> 2 | V90: =COUNTIF(G90:J90,"*Hate Speech*") -> 0 | W90: =SUM(T90:V90)/4 -> 1 | X90: =IF(T90>2,"Normal", IF(U90>2, "Offensive", IF(V90>2, "Hate Speech"))) -> FALSE | Y90: =STDEV(T90:V90) -> 1.1547005
... A96: 095 | B96: 21990566_gab | C96: this kike is still alive wtf | D96: Jewish | E96: Jewish | F96: Jewish people | G96: Offensive | H96: Hate Speech | I96: Hate Speech | J96: Hate Speech | K96: GM#5 | L96: GM#1 | M96: Gab | N96: hatespeech | O96: Jewish | P96: hatespeech | Q96: Jewish | R96: hatespeech | S96: Jewish | T96: =COUNTIF(G96:J96,"*Normal*") -> 0 | U96: =COUNTIF(G96:J96,"*Offensive*") -> 1 | V96: =COUNTIF(G96:J96,"*Hate Speech*") -> 3 | W96: =SUM(T96:V96)/4 -> 1 | X96: =IF(T96>2,"Normal", IF(U96>2, "Offensive", IF(V96>2, "Hate Speech"))) -> Hate Speech | Y96: =STDEV(T96:V96) -> 1.5275252
A97: 096 | B97: 1179094368986247169_twitter | C97: week <number> <number> cannibal holocaust <number> demons <number> all the colors of the dark <number> blood and black lace <number> zombie or zombi <number> title for this is a mess it is the one directed by lucio fulci <number> sat tigers are not afraid <number> sun the devils <number> | D97: None | E97: None | F97: N/A | H97: Normal | I97: Normal | J97: Normal | K97: GM#5 | L97: GM#2 | M97: Twitter | N97: normal | O97: None | P97: normal | Q97: None | R97: normal | S97: None | T97: =COUNTIF(G97:J97,"*Normal*") -> 3 | U97: =COUNTIF(G97:J97,"*Offensive*") -> 0 | V97: =COUNTIF(G97:J97,"*Hate Speech*") -> 0 | W97: =SUM(T97:V97)/4 -> 0.75 | X97: =IF(T97>2,"Normal", IF(U97>2, "Offensive", IF(V97>2, "Hate Speech"))) -> Normal | Y97: =STDEV(T97:V97) -> 1.7320508
A98: 097 | B98: 10840200_gab | C98: rep steve cohen of tennessee announced thursday he is introducing articles of impeachment against president trump following the violence in virginia gabfam | D98: None | E98: None | F98: N/A | G98: Normal | H98: Normal | I98: Offensive | J98: Normal | K98: GM#5 | L98: GM#4 | M98: Gab | N98: normal | O98: None | P98: normal | Q98: None | R98: normal | S98: None | T98: =COUNTIF(G98:J98,"*Normal*") -> 3 | U98: =COUNTIF(G98:J98,"*Offensive*") -> 1 | V98: =COUNTIF(G98:J98,"*Hate Speech*") -> 0 | W98: =SUM(T98:V98)/4 -> 1 | X98: =IF(T98>2,"Normal", IF(U98>2, "Offensive", IF(V98>2, "Hate Speech"))) -> Normal | Y98: =STDEV(T98:V98) -> 1.5275252
A99: 098 | B99: 1178881031136403456_twitter | C99: lrt the loud white dude is a fucking fed right like no fucking question | D99: None | E99: - | F99: N/A | G99: Offensive | H99: Normal | I99: Offensive | J99: Normal | K99: GM#5 | L99: GM#3 | M99: Twitter | N99: normal | O99: None | P99: normal | Q99: None | R99: normal | S99: None | T99: =COUNTIF(G99:J99,"*Normal*") -> 2 | U99: =COUNTIF(G99:J99,"*Offensive*") -> 2 | V99: =COUNTIF(G99:J99,"*Hate Speech*") -> 0 | W99: =SUM(T99:V99)/4 -> 1 | X99: =IF(T99>2,"Normal", IF(U99>2, "Offensive", IF(V99>2, "Hate Speech"))) -> FALSE | Y99: =STDEV(T99:V99) -> 1.1547005
A100: 099 | B100: 14375797_gab | C100: pres johnson buying into the stereotype that blacks were afraid of snakes who is not afraid of snakes he d drive to gas stations with one in his trunk and try to trick black attendants into opening it | D100: African | E100: AfricanBlack | F100: Black people | G100: Normal | H100: Offensive | I100: Hate Speech | J100: Hate Speech | K100: GM#5 | L100: GM#1 | M100: Gab | N100: normal | O100: Men, Women | P100: normal | Q100: African | R100: normal | S100: African | T100: =COUNTIF(G100:J100,"*Normal*") -> 1 | U100: =COUNTIF(G100:J100,"*Offensive*") -> 1 | V100: =COUNTIF(G100:J100,"*Hate Speech*") -> 2 | W100: =SUM(T100:V100)/4 -> 1 | X100: =IF(T100>2,"Normal", IF(U100>2, "Offensive", IF(V100>2, "Hate Speech"))) -> FALSE | Y100: =STDEV(T100:V100) -> 0.57735027
A101: 100 | B101: 1178942716459151360_twitter | C101: <user> i can not decide darlifra is a fucking conservative nightmare but cross ange makes a rape victim apologize for being raped among many egregious offenses it like choosing between burning at the stake and being caught in a volcanic explosion | D101: None | E101: Muslim / Arab | F101: Women | H101: Normal | I101: Offensive | J101: Offensive | K101: GM#5 | L101: GM#2 | M101: Twitter | N101: normal | O101: None | P101: normal | Q101: None | R101: normal | S101: None | T101: =COUNTIF(G101:J101,"*Normal*") -> 1 | U101: =COUNTIF(G101:J101,"*Offensive*") -> 2 | V101: =COUNTIF(G101:J101,"*Hate Speech*") -> 0 | W101: =SUM(T101:V101)/4 -> 0.75 | X101: =IF(T101>2,"Normal", IF(U101>2, "Offensive", IF(V101>2, "Hate Speech"))) -> FALSE | Y101: =STDEV(T101:V101) -> 1
A102: 101 | B102: 27841553_gab | C102: let me go to bed nazi faggot maybe i can catch you off guard again tonight do not mute lol that will not help <user> | D102: Homosexual | E102: Gay people, Nazis | F102: Gay people, Jewish people | G102: Offensive | H102: Hate Speech | I102: Hate Speech | J102: Offensive | K102: GM#4 | L102: GM#3 | M102: Gab | N102: offensive | O102: Other | P102: offensive | Q102: Homosexual | R102: offensive | S102: Homosexual, Caucasian | T102: =COUNTIF(G102:J102,"*Normal*") -> 0 | U102: =COUNTIF(G102:J102,"*Offensive*") -> 2 | V102: =COUNTIF(G102:J102,"*Hate Speech*") -> 2 | W102: =SUM(T102:V102)/4 -> 1 | X102: =IF(T102>2,"Normal", IF(U102>2, "Offensive", IF(V102>2, "Hate Speech"))) -> FALSE | Y102: =STDEV(T102:V102) -> 1.1547005
A103: 102 | B103: 8073987_gab | C103: swedish men are all silent as their woman are being raped to death by niggers | D103: Black | E103: AfricanBlack | F103: Black people, Women | G103: Offensive | H103: Hate Speech | I103: Hate Speech | J103: Hate Speech | K103: GM#4 | L103: GM#1 | M103: Gab | N103: offensive | O103: Women | P103: offensive | Q103: African, Women | R103: hatespeech | S103: African | T103: =COUNTIF(G103:J103,"*Normal*") -> 0 | U103: =COUNTIF(G103:J103,"*Offensive*") -> 1 | V103: =COUNTIF(G103:J103,"*Hate Speech*") -> 3 | W103: =SUM(T103:V103)/4 -> 1 | X103: =IF(T103>2,"Normal", IF(U103>2, "Offensive", IF(V103>2, "Hate Speech"))) -> Hate Speech | Y103: =STDEV(T103:V103) -> 1.5275252
A104: 103 | B104: 1177662316835475457_twitter | C104: <user> <user> <user> it called capitalism towel head go back to your communist country and see how that works out | D104: Immigrant | E104: Women | F104: Middle Eastern people | G104: Offensive | H104: Offensive | I104: Hate Speech | J104: Hate Speech | K104: GM#4 | L104: GM#2 | M104: Twitter | N104: hatespeech | O104: Refugee | P104: offensive | Q104: Economic | R104: normal | S104: None | T104: =COUNTIF(G104:J104,"*Normal*") -> 0 | U104: =COUNTIF(G104:J104,"*Offensive*") -> 2 | V104: =COUNTIF(G104:J104,"*Hate Speech*") -> 2 | W104: =SUM(T104:V104)/4 -> 1 | X104: =IF(T104>2,"Normal", IF(U104>2, "Offensive", IF(V104>2, "Hate Speech"))) -> FALSE | Y104: =STDEV(T104:V104) -> 1.1547005
A105: 104 | B105: 18796136_gab | C105: the ultimate anti muslim weapon a muslim being killed by a women means no virgins in heaven the armed kurdish women brigades caused fear and running of isis in syria this is the time for our sisters to take control of the destiny of the human race | D105: Muslim | E105: Muslim people | F105: Muslims | G105: Offensive | I105: Hate Speech | J105: Hate Speech | K105: GM#4 | L105: GM#5 | M105: Gab | N105: offensive | O105: Islam, Women | P105: hatespeech | Q105: Islam | R105: offensive | S105: Islam | T105: =COUNTIF(G105:J105,"*Normal*") -> 0 | U105: =COUNTIF(G105:J105,"*Offensive*") -> 1 | V105: =COUNTIF(G105:J105,"*Hate Speech*") -> 2 | W105: =SUM(T105:V105)/4 -> 0.75 | X105: =IF(T105>2,"Normal", IF(U105>2, "Offensive", IF(V105>2, "Hate Speech"))) -> FALSE | Y105: =STDEV(T105:V105) -> 1
A106: 105 | B106: 1179033415279988738_twitter | C106: <user> oh wow just learned this word through you but did they use it as an apropiation it to make it stop hurting them like bi guys could do w faggot or did they just use it in a derogatory way | D106: None | E106: - | F106: N/A | G106: Normal | H106: Offensive | I106: Offensive | J106: Normal | K106: GM#4 | L106: GM#3 | M106: Twitter | N106: normal | O106: None | P106: normal | Q106: None | R106: normal | S106: Other, Homosexual | T106: =COUNTIF(G106:J106,"*Normal*") -> 2 | U106: =COUNTIF(G106:J106,"*Offensive*") -> 2 | V106: =COUNTIF(G106:J106,"*Hate Speech*") -> 0 | W106: =SUM(T106:V106)/4 -> 1 | X106: =IF(T106>2,"Normal", IF(U106>2, "Offensive", IF(V106>2, "Hate Speech"))) -> FALSE | Y106: =STDEV(T106:V106) -> 1.1547005
A107: 106 | B107: 19939869_gab | C107: nigger lovin fgt | D107: Black, Homosexual | E107: AfricanBlack, Homosexual | F107: Black people, Gay people | G107: Offensive | H107: Offensive | I107: Hate Speech | J107: Hate Speech | K107: GM#4 | L107: GM#1 | M107: Gab | N107: offensive | O107: African, Homosexual | P107: offensive | Q107: African, Homosexual | R107: offensive | S107: African, Homosexual | T107: =COUNTIF(G107:J107,"*Normal*") -> 0 | U107: =COUNTIF(G107:J107,"*Offensive*") -> 2 | V107: =COUNTIF(G107:J107,"*Hate Speech*") -> 2 | W107: =SUM(T107:V107)/4 -> 1 | X107: =IF(T107>2,"Normal", IF(U107>2, "Offensive", IF(V107>2, "Hate Speech"))) -> FALSE | Y107: =STDEV(T107:V107) -> 1.1547005
A108: 107 | B108: 1082488743037145089_twitter | C108: sick of bitches bitching about other bitches being bitches | D108: Woman | E108: Liberals / Media | F108: Women | G108: Offensive | H108: Normal | I108: Offensive | J108: Offensive | K108: GM#4 | L108: GM#2 | M108: Twitter | N108: offensive | O108: Women | P108: offensive | Q108: Women | R108: offensive | S108: Women | T108: =COUNTIF(G108:J108,"*Normal*") -> 1 | U108: =COUNTIF(G108:J108,"*Offensive*") -> 3 | V108: =COUNTIF(G108:J108,"*Hate Speech*") -> 0 | W108: =SUM(T108:V108)/4 -> 1 | X108: =IF(T108>2,"Normal", IF(U108>2, "Offensive", IF(V108>2, "Hate Speech"))) -> Offensive | Y108: =STDEV(T108:V108) -> 1.5275252
A109: 108 | B109: 14896755_gab | C109: and he was given a traditional moslem sea burial | D109: None | E109: - | F109: N/A | G109: Normal | H109: Normal | I109: Normal | J109: Normal | K109: GM#4 | L109: GM#5 | M109: Gab | N109: normal | O109: None | P109: normal | Q109: None | R109: normal | S109: None | T109: =COUNTIF(G109:J109,"*Normal*") -> 4 | U109: =COUNTIF(G109:J109,"*Offensive*") -> 0 | V109: =COUNTIF(G109:J109,"*Hate Speech*") -> 0 | W109: =SUM(T109:V109)/4 -> 1 | X109: =IF(T109>2,"Normal", IF(U109>2, "Offensive", IF(V109>2, "Hate Speech"))) -> Normal | Y109: =STDEV(T109:V109) -> 2.3094011
A110: 109 | B110: 11983762_gab | C110: open invitation to all queers to my christian island republic for public death 1 fags | D110: Homosexual | E110: Gay people | F110: LGBTQ+ people | G110: Hate Speech | H110: Hate Speech | I110: Hate Speech | J110: Hate Speech | K110: GM#4 | L110: GM#3 | M110: Gab | N110: hatespeech | O110: Other | P110: hatespeech | Q110: Homosexual | R110: normal | S110: None | T110: =COUNTIF(G110:J110,"*Normal*") -> 0 | U110: =COUNTIF(G110:J110,"*Offensive*") -> 0 | V110: =COUNTIF(G110:J110,"*Hate Speech*") -> 4 | W110: =SUM(T110:V110)/4 -> 1 | X110: =IF(T110>2,"Normal", IF(U110>2, "Offensive", IF(V110>2, "Hate Speech"))) -> Hate Speech | Y110: =STDEV(T110:V110) -> 2.3094011
A111: 110 | B111: 1275492309170376713_twitter | C111: it ’ bad enough the caucasians shade me for my name but my own ppl be mocking me the spelling is different 😡 | D111: None | E111: Caucasian | F111: N/A | G111: Normal | H111: Normal | I111: Offensive | J111: Normal | K111: GM#4 | L111: GM#1 | M111: Twitter | N111: normal | O111: African, Caucasian | P111: normal | Q111: None | R111: offensive | S111: Caucasian | T111: =COUNTIF(G111:J111,"*Normal*") -> 3 | U111: =COUNTIF(G111:J111,"*Offensive*") -> 1 | V111: =COUNTIF(G111:J111,"*Hate Speech*") -> 0 | W111: =SUM(T111:V111)/4 -> 1 | X111: =IF(T111>2,"Normal", IF(U111>2, "Offensive", IF(V111>2, "Hate Speech"))) -> Normal | Y111: =STDEV(T111:V111) -> 1.5275252
A112: 111 | B112: 13653444_gab | C112: regular morning joe contributor mark halperin is fascinated enough to tweet about the new iphone calculator that been out for weeks stay retarded libs | D112: Liberal, Disabled | E112: None (self-directed) | F112: N/A | G112: Offensive | H112: Offensive | I112: Offensive | J112: Normal | K112: GM#4 | L112: GM#2 | M112: Gab | N112: offensive | O112: Other | P112: offensive | Q112: Other | R112: offensive | S112: Other | T112: =COUNTIF(G112:J112,"*Normal*") -> 1 | U112: =COUNTIF(G112:J112,"*Offensive*") -> 3 | V112: =COUNTIF(G112:J112,"*Hate Speech*") -> 0 | W112: =SUM(T112:V112)/4 -> 1 | X112: =IF(T112>2,"Normal", IF(U112>2, "Offensive", IF(V112>2, "Hate Speech"))) -> Offensive | Y112: =STDEV(T112:V112) -> 1.5275252
A113: 112 | B113: 6692146_gab | C113: democrats have next obama readying in the wings a muslim doctor that what they call diversity i call it stupid 👹 | D113: Muslim | E113: Muslim people | F113: Muslims | G113: Offensive | H113: Normal | I113: Hate Speech | J113: Hate Speech | K113: GM#4 | L113: GM#5 | M113: Gab | N113: offensive | O113: Islam, Other | P113: normal | Q113: Islam | R113: offensive | S113: Islam, Other | T113: =COUNTIF(G113:J113,"*Normal*") -> 1 | U113: =COUNTIF(G113:J113,"*Offensive*") -> 1 | V113: =COUNTIF(G113:J113,"*Hate Speech*") -> 2 | W113: =SUM(T113:V113)/4 -> 1 | X113: =IF(T113>2,"Normal", IF(U113>2, "Offensive", IF(V113>2, "Hate Speech"))) -> FALSE | Y113: =STDEV(T113:V113) -> 0.57735027
A114: 113 | B114: 1178582515457708032_twitter | C114: lh wtf i am weak this girl retarded lmfao | D114: Disabled | E114: People with disabilities | F114: People with disabilities | G114: Offensive | H114: Offensive | I114: Offensive | J114: Offensive | K114: GM#4 | L114: GM#3 | M114: Twitter | N114: offensive | O114: Other, Women | P114: offensive | Q114: Disability | R114: offensive | S114: Disability | T114: =COUNTIF(G114:J114,"*Normal*") -> 0 | U114: =COUNTIF(G114:J114,"*Offensive*") -> 4 | V114: =COUNTIF(G114:J114,"*Hate Speech*") -> 0 | W114: =SUM(T114:V114)/4 -> 1 | X114: =IF(T114>2,"Normal", IF(U114>2, "Offensive", IF(V114>2, "Hate Speech"))) -> Offensive | Y114: =STDEV(T114:V114) -> 2.3094011
A115: 114 | B115: 1179071111713017861_twitter | C115: <user> the home minister is creating a system of second class citizens within our country muslim refugee is no different from a hindu christian one no divide and rule | D115: Refugee | E115: Muslim, Refugee, Immigrant | F115: N/A | G115: Offensive | H115: Normal | I115: Normal | J115: Normal | K115: GM#4 | L115: GM#1 | M115: Twitter | N115: normal | O115: None | P115: normal | Q115: None | R115: normal | S115: None | T115: =COUNTIF(G115:J115,"*Normal*") -> 3 | U115: =COUNTIF(G115:J115,"*Offensive*") -> 1 | V115: =COUNTIF(G115:J115,"*Hate Speech*") -> 0 | W115: =SUM(T115:V115)/4 -> 1 | X115: =IF(T115>2,"Normal", IF(U115>2, "Offensive", IF(V115>2, "Hate Speech"))) -> Normal | Y115: =STDEV(T115:V115) -> 1.5275252
A116: 115 | B116: 1186068758013599744_twitter | C116: you ever just not want to be alive anymore not kill yourself necessarily but just stop the life you have | D116: None | E116: Women, Latino | F116: N/A | G116: Normal | H116: Normal | I116: Normal | J116: Normal | K116: GM#4 | L116: GM#2 | M116: Twitter | N116: normal | O116: None | P116: normal | Q116: Other | R116: normal | S116: None | T116: =COUNTIF(G116:J116,"*Normal*") -> 4 | U116: =COUNTIF(G116:J116,"*Offensive*") -> 0 | V116: =COUNTIF(G116:J116,"*Hate Speech*") -> 0 | W116: =SUM(T116:V116)/4 -> 1 | X116: =IF(T116>2,"Normal", IF(U116>2, "Offensive", IF(V116>2, "Hate Speech"))) -> Normal | Y116: =STDEV(T116:V116) -> 2.3094011
A117: 116 | B117: 1094643815028273152_twitter | C117: <user> what type of muslims are these funded by the hateful saudi wahabi govt | D117: None | E117: - | F117: N/A | G117: Normal | I117: Hate Speech | J117: Normal | K117: GM#4 | L117: GM#5 | M117: Twitter | N117: offensive | O117: Arab, Islam | P117: normal | Q117: Men, Women | R117: hatespeech | S117: Islam | T117: =COUNTIF(G117:J117,"*Normal*") -> 2 | U117: =COUNTIF(G117:J117,"*Offensive*") -> 0 | V117: =COUNTIF(G117:J117,"*Hate Speech*") -> 1 | W117: =SUM(T117:V117)/4 -> 0.75 | X117: =IF(T117>2,"Normal", IF(U117>2, "Offensive", IF(V117>2, "Hate Speech"))) -> FALSE | Y117: =STDEV(T117:V117) -> 1
A118: 117 | B118: 1178819638504775681_twitter | C118: <user> <user> <user> <user> <user> it not for black people to decide whether black can be racist or not just like its not white to decide whether white can be racist or not tariq nasheed called asians as inbred race and indians as sand ni goatfucker that is not racist | D118: Asian | E118: Indian/Asian, Arab people | F118: N/A | G118: Offensive | H118: Offensive | I118: Hate Speech | J118: Normal | K118: GM#4 | L118: GM#3 | M118: Twitter | N118: normal | O118: None | P118: normal | Q118: None | R118: normal | S118: None | T118: =COUNTIF(G118:J118,"*Normal*") -> 1 | U118: =COUNTIF(G118:J118,"*Offensive*") -> 2 | V118: =COUNTIF(G118:J118,"*Hate Speech*") -> 1 | W118: =SUM(T118:V118)/4 -> 1 | X118: =IF(T118>2,"Normal", IF(U118>2, "Offensive", IF(V118>2, "Hate Speech"))) -> FALSE | Y118: =STDEV(T118:V118) -> 0.57735027
A119: 118 | B119: 1091863937673580545_twitter | C119: right ngl lads lets censor the shit before stick up they ass bitches run rampant | D119: Woman | E119: Woman | F119: Women | G119: Offensive | H119: Offensive | I119: Offensive | J119: Offensive | K119: GM#4 | L119: GM#1 | M119: Twitter | N119: offensive | O119: Other | P119: normal | Q119: African | R119: offensive | S119: Other | T119: =COUNTIF(G119:J119,"*Normal*") -> 0 | U119: =COUNTIF(G119:J119,"*Offensive*") -> 4 | V119: =COUNTIF(G119:J119,"*Hate Speech*") -> 0 | W119: =SUM(T119:V119)/4 -> 1 | X119: =IF(T119>2,"Normal", IF(U119>2, "Offensive", IF(V119>2, "Hate Speech"))) -> Offensive | Y119: =STDEV(T119:V119) -> 2.3094011
...

Sheet Feuille 2
A1: Old Target Group Labels: | B1: New Target Group Labels: | C1: COUNT:
A2: African | B2: African | C2: =COUNTIF('Feuille 1'!D2:D501,"*African*") -> 33
A3: Black | B3: Black | C3: =COUNTIF('Feuille 1'!D2:D501,"*Black*") -> 57
A4: Chinese | B4: Chinese | C4: =COUNTIF('Feuille 1'!D2:D501,"*Chinese*") -> 4
A5: Asians | B5: Asian | C5: =COUNTIF('Feuille 1'!D2:D501,"*Asian*") -> 16
A6: Brown | B6: Brown | C6: =COUNTIF('Feuille 1'!D2:D501,"*Brown*") -> 2
A7: Arab | B7: Arab | C7: =COUNTIF('Feuille 1'!D2:D501,"*Arab*") -> 11
A8: Caucasians | B8: Caucasian | C8: =COUNTIF('Feuille 1'!D2:D501,"*Caucasian*") -> 9
A9: White
A10: Jewish | B10: Jewish | C10: =COUNTIF('Feuille 1'!D2:D501,"*Jewish*") -> 34
A11: Mexican | B11: Mexican | C11: =COUNTIF('Feuille 1'!D2:D501,"*Mexican*") -> 1
A12: Hispanics | B12: Hispanic | C12: =COUNTIF('Feuille 1'!D2:D501,"*Hispanic*") -> 2
A13: Latino | B13: Latino | C13: =COUNTIF('Feuille 1'!D2:D501,"*Latin*") -> 4
A14: Native Americans | B14: Native American | C14: =COUNTIF('Feuille 1'!D2:D501,"*Native American*") -> 1
A15: Australians | B15: Australian | C15: =COUNTIF('Feuille 1'!D2:D501,"*Australian*") -> 1
A16: Indians | B16: Indian | C16: =COUNTIF('Feuille 1'!D2:D501,"*Indian*") -> 1
A17: Somali | B17: Somali | C17: =COUNTIF('Feuille 1'!D2:D501,"*Somali*") -> 1
A18: Biracial | B18: Biracial | C18: =COUNTIF('Feuille 1'!D2:D501,"*Biracial*") -> 1
A19: Muslims | B19: Muslim | C19: =COUNTIF('Feuille 1'!D2:D501,"*Muslim*") -> 57
A20: Islam
A21: Homosexual | B21: Homosexual | C21: =COUNTIF('Feuille 1'!D2:D501,"*Homosexual*") -> 62
A22: Trans | B22: Trans | C22: =COUNTIF('Feuille 1'!D2:D501,"*Trans*") -> 3
A23: Queer | B23: Queer | C23: =COUNTIF('Feuille 1'!D2:D501,"*Queer*") -> 4
A24: Liberals | B24: Liberal | C24: =COUNTIF('Feuille 1'!D2:D501,"*Liberal*") -> 7
A25: Communists | B25: Communist | C25: =COUNTIF('Feuille 1'!D2:D501,"*Communist*") -> 1
A26: Right-wing | B26: Right-wing | C26: =COUNTIF('Feuille 1'!D2:D501,"*Right-wing*") -> 1
A27: Democrats | B27: Democrat | C27: =COUNTIF('Feuille 1'!D2:D501,"*Democrat*") -> 1
A28: Pro-nazi/nazi | B28: Pro-nazi/nazi | C28: =COUNTIF('Feuille 1'!D2:D501,"*Pro-nazi/nazi*") -> 3
A29: Disability | B29: Disability | C29: =COUNTIF('Feuille 1'!D2:D501,"*Disability*") -> 4
A30: Rich | B30: Economic Status | C30: =COUNTIF('Feuille 1'!D2:D501,"*Economic Status*") -> 8
A31: Working Class
A32: Economic
A33: Men | B33: Men | C33: =COUNTIF('Feuille 1'!D2:D501,"*Men*") -> 3
A34: Women | B34: Woman | C34: =COUNTIF('Feuille 1'!D2:D501,"*Woman*") -> 59
A35: Victims of SA | B35: Victims of SA | C35: =COUNTIF('Feuille 1'!D2:D501,"*Victims of SA*") -> 1
A36: Immigrants | B36: Immigrant | C36: =COUNTIF('Feuille 1'!D2:D501,"*Immigrant*") -> 18
A37: Refugees | B37: Refugee | C37: =COUNTIF('Feuille 1'!D2:D501,"*Refugee*") -> 6
A38: Protestors | B38: Protestor | C38: =COUNTIF('Feuille 1'!D2:D501,"*Protestor*") -> 1
A39: Journalists | B39: Journalist | C39: =COUNTIF('Feuille 1'!D2:D501,"*Journalist*") -> 2
A40: Uneducated | B40: Education | C40: =COUNTIF('Feuille 1'!D2:D501,"*Education*") -> 1
A41: Police | B41: Police | C41: =COUNTIF('Feuille 1'!D2:D501,"*Police*") -> 1
A42: None | B42: None | C42: =COUNTIF('Feuille 1'!D2:D501,"*None*") -> 136

Sheet Findings
A1: Annotation Convergence Analysis | Decoding Biases in AI
A2: Comparing Grok, Claude, and five human annotators (H1, H2, SA1, SA2, SA3) | N = 500 posts
A4: 1 | Classification Distribution by Annotator
A5: Annotator | B5: Normal | C5: Offensive | D5: Hate Speech | E5: Total Valid
A6: Grok | B6: 62 (12.4%) | C6: 201 (40.2%) | D6: 237 (47.4%) | E6: 500
A7: Claude | B7: 213 (42.6%) | C7: 114 (22.8%) | D7: 173 (34.6%) | E7: 500 | I7: CLAUDE | L7: TOTAL
A8: H1 | B8: 201 (41.3%) | C8: 250 (51.3%) | D8: 36 (7.4%) | E8: 487 | I8: NORMAL | J8: OFFENSIVE | K8: HATE SPEECH
A9: H2 | B9: 196 (39.8%) | C9: 253 (51.4%) | D9: 43 (8.7%) | E9: 492 | G9: GROK | H9: NORMAL | I9: 61 | J9: 1 | K9: 0 | L9: 62
A10: SA1 | B10: 188 (37.6%) | C10: 176 (35.2%) | D10: 136 (27.2%) | E10: 500 | H10: OFFENSIVE | I10: 90 | J10: 95 | K10: 16 | L10: 201
A11: SA2 | B11: 193 (38.6%) | C11: 161 (32.2%) | D11: 146 (29.2%) | E11: 500 | H11: HATE SPEECH | I11: 62 | J11: 18 | K11: 157 | L11: 237
A12: SA3 | B12: 179 (35.8%) | C12: 166 (33.2%) | D12: 155 (31.0%) | E12: 500 | G12: TOTAL | I12: 213 | J12: 114 | K12: 173 | L12: 500
A16: Cross-tabulation: Grok vs Claude (absolute counts) | G16: Metric | H16: Count | I16: % of valid n
A17: Grok \ Claude → | B17: Hate Speech | C17: Offensive | D17: Normal | E17: Row Total | G17: Overall Agreement (exact match) | H17: 313 | I17: 62.6%
A18: Hate Speech | B18: 157 | C18: 18 | D18: 62 | E18: 237 | G18: Hate Speech agreement | H18: 157 | I18: 66.2%
A19: Offensive | B19: 16 | C19: 95 | D19: 90 | E19: 201 | G19: Offensive agreement | H19: 95 | I19: 47.3%
A20: Normal | B20: 0 | C20: 1 | D20: 61 | E20: 62 | G20: Normal agreement | H20: 61 | I20: 98.4%
A21: Column Total | B21: 173 | C21: 114 | D21: 213 | E21: 500 | G21: Overall Disagreement | H21: 187 | I21: 37.4%
A23: Cross-tabulation: Grok vs Group Consensus (H1+H2 only) | G23: Metric | H23: Count | I23: % of valid n
A24: Grok \ Human → | B24: Hate Speech | C24: Offensive | D24: Normal | E24: Row Total | G24: Overall Agreement (exact match) | H24: 134 | I24: 38.4%
A25: Hate Speech | B25: 16 | C25: 113 | D25: 24 | E25: 153 | G25: Hate Speech agreement | H25: 16 | I25: 10.5%
A26: Offensive | B26: 2 | C26: 70 | D26: 73 | E26: 145 | G26: Offensive agreement | H26: 70 | I26: 48.3%
A27: Offensive | B27: 2 | C27: 1 | D27: 48 | E27: 51 | G27: Normal agreement | H27: 48 | I27: 94.1%
A28: Column Total | B28: 20 | C28: 184 | D28: 145 | E28: 349 | G28: Overall Disagreement | H28: 215 | I28: 61.6%
A30: Cross-tabulation: Claude vs Group Consensus (H1+H2 only) | G30: Metric | H30: Count | I30: % of valid n
A31: Claude \ Human → | B31: Hate Speech | C31: Offensive | D31: Normal | E31: Row Total | G31: Overall Agreement (exact match) | H31: 188 | I31: 53.9%
A32: Hate Speech | B32: 14 | C32: 97 | D32: 9 | E32: 120 | G32: Hate Speech agreement | H32: 14 | I32: 11.7%
A33: Offensive | B33: 5 | C33: 55 | D33: 17 | E33: 77 | G33: Offensive agreement | H33: 55 | I33: 71.4%
A34: Normal | B34: 1 | C34: 32 | D34: 119 | E34: 152 | G34: Normal agreement | H34: 119 | I34: 78.3%
A35: Column Total | B35: 20 | C35: 184 | D35: 145 | E35: 349 | G35: Overall Disagreement | H35: 161 | I35: 46.1%
I38: HUMAN CONSENUS | L38: TOTAL
I39: NORMAL | J39: OFFENSIVE | K39: HATE SPEECH
G40: GROK | H40: NORMAL | I40: 48 | J40: 1 | K40: 2 | L40: 51
H41: OFFENSIVE | I41: 73 | J41: 70 | K41: 2 | L41: 145
H42: HATE SPEECH | I42: 24 | J42: 113 | K42: 16 | L42: 153
G43: TOTAL | I43: 145 | J43: 184 | K43: 20 | L43: 349
I45: HUMAN CONSENUS | L45: TOTAL
I46: NORMAL | J46: OFFENSIVE | K46: HATE SPEECH
G47: CLAUDE | H47: NORMAL | I47: 119 | J47: 32 | K47: 1 | L47: 152
H48: OFFENSIVE | I48: 17 | J48: 55 | K48: 5 | L48: 77
H49: HATE SPEECH | I49: 9 | J49: 97 | K49: 14 | L49: 120
G50: TOTAL | I50: 145 | J50: 184 | K50: 20 | L50: 349
A60: PAIRWISE INTER-ANNOTATOR AGREEMENT (Group Members)
A61: Pair | B61: N (valid) | C61: Agreement % | D61: Cohen's κ
A62: N & M | B62: 49 | C62: 83.7% | D62: 0.704
A63: N & C | B63: 46 | C63: 67.4% | D63: 0.478
A64: N & T | B64: 48 | C64: 77.1% | D64: 0.590
A65: N & A | B65: 46 | C65: 67.4% | D65: 0.425
A66: M & C | B66: 48 | C66: 72.9% | D66: 0.514
A67: M & T | B67: 50 | C67: 74.0% | D67: 0.501
A68: M & A | B68: 49 | C68: 73.5% | D68: 0.543
A69: C & T | B69: 48 | C69: 62.5% | D69: 0.344
A70: C & A | B70: 48 | C70: 68.8% | D70: 0.438
A71: T & A | B71: 48 | C71: 79.2% | D71: 0.598
A72: Mean | B72: 48 | C72: 72.6% | D72: 0.513
A74: 5×5 PAIRWISE AGREEMENT MATRIX (% exact match)
B75: N | C75: M | D75: C | E75: T | F75: A
A76: N | B76: - | C76: 83.7% | D76: 67.4% | E76: 77.1% | F76: 67.4%
A77: M | B77: 83.7% | C77: - | D77: 72.9% | E77: 74.0% | F77: 73.5%
A78: C | B78: 67.4% | C78: 72.9% | D78: - | E78: 62.5% | F78: 68.8%
A79: T | B79: 77.1% | C79: 74.0% | D79: 62.5% | E79: - | F79: 79.2%
A80: A | B80: 67.4% | C80: 73.5% | D80: 68.8% | E80: 79.2% | F80: -
A82: 5×5 PAIRWISE COHEN'S KAPPA MATRIX
B83: N | C83: M | D83: C | E83: T | F83: A
A84: N | B84: - | C84: 0.704 | D84: 0.478 | E84: 0.590 | F84: 0.425
A85: M | B85: 0.704 | C85: - | D85: 0.514 | E85: 0.501 | F85: 0.543
A86: C | B86: 0.478 | C86: 0.514 | D86: - | E86: 0.344 | F86: 0.438
A87: T | B87: 0.590 | C87: 0.501 | D87: 0.344 | E87: - | F87: 0.598
A88: A | B88: 0.425 | C88: 0.543 | D88: 0.438 | E88: 0.598 | F88: -
A90: 8 | Summary Statistics & Aggregate Per-Class Agreement
A91: Metric | B91: Value | C91: Notes
A92: Mean pairwise agreement | B92: 72.6% | C92: across 10 pairs
A93: Agreement range | B93: 62.5% – 83.7% | C93: C&T low; N&M high
A94: Mean Cohen's κ | B94: 0.513 | C94: Moderate
A95: Cohen's κ range | B95: 0.344 – 0.704 | C95: Fair to substantial
A96: Pooled Cohen's κ | B96: 0.518 | C96: all 10 pairs combined
A98: AGGREGATE PER CLASS AGREEMENT (pooled across all 10 pairs)
A99: Label | B99: Agreements | C99: Total | D99: Agreement %
A100: Normal | B100: 290 | C100: 386 | D100: 75.1%
A101: Offensive | B101: 368 | C101: 495 | D101: 74.3%
A102: Hate Speech | B102: 40 | C102: 79 | D102: 50.6%

Sheet Feuille 4
